[
	{
		"CategoryName": "Home & Garden > Bathroom Accessories > Bath Caddies"
	},
	{
		"CategoryName": "Home & Garden > Bathroom Accessories > Bath Mats & Rugs"
	},
	{
		"CategoryName": "Home & Garden > Bathroom Accessories > Bath Pillows"
	},
	{
		"CategoryName": "Home & Garden > Bathroom Accessories > Bathroom Accessory Mounts"
	},
	{
		"CategoryName": "Home & Garden > Bathroom Accessories > Bathroom Accessory Sets"
	},
	{
		"CategoryName": "Home & Garden > Bathroom Accessories > Facial Tissue Holders"
	},
	{
		"CategoryName": "Home & Garden > Bathroom Accessories > Hand Dryer Accessories"
	},
	{
		"CategoryName": "Home & Garden > Bathroom Accessories > Hand Dryers"
	},
	{
		"CategoryName": "Home & Garden > Bathroom Accessories > Medicine Cabinets"
	},
	{
		"CategoryName": "Home & Garden > Bathroom Accessories > Robe Hooks"
	},
	{
		"CategoryName": "Home & Garden > Bathroom Accessories > Safety Grab Bars"
	},
	{
		"CategoryName": "Home & Garden > Bathroom Accessories > Shower Curtain Rings"
	},
	{
		"CategoryName": "Home & Garden > Bathroom Accessories > Shower Curtains"
	},
	{
		"CategoryName": "Home & Garden > Bathroom Accessories > Shower Rods"
	},
	{
		"CategoryName": "Home & Garden > Bathroom Accessories > Soap & Lotion Dispensers"
	},
	{
		"CategoryName": "Home & Garden > Bathroom Accessories > Soap Dishes & Holders"
	},
	{
		"CategoryName": "Home & Garden > Bathroom Accessories > Toilet Brush Replacement Heads"
	},
	{
		"CategoryName": "Home & Garden > Bathroom Accessories > Toilet Brushes & Holders"
	},
	{
		"CategoryName": "Home & Garden > Bathroom Accessories > Toilet Paper Holders"
	},
	{
		"CategoryName": "Home & Garden > Bathroom Accessories > Toothbrush Holders"
	},
	{
		"CategoryName": "Home & Garden > Bathroom Accessories > Towel Racks & Holders"
	},
	{
		"CategoryName": "Home & Garden > Business & Home Security > Dummy Surveillance Cameras"
	},
	{
		"CategoryName": "Home & Garden > Business & Home Security > Home Alarm Systems"
	},
	{
		"CategoryName": "Home & Garden > Business & Home Security > Motion Sensors"
	},
	{
		"CategoryName": "Home & Garden > Business & Home Security > Safety & Security Mirrors"
	},
	{
		"CategoryName": "Home & Garden > Business & Home Security > Security Lights"
	},
	{
		"CategoryName": "Home & Garden > Business & Home Security > Security Monitors & Recorders"
	},
	{
		"CategoryName": "Home & Garden > Business & Home Security > Security Safe Accessories"
	},
	{
		"CategoryName": "Home & Garden > Business & Home Security > Security Safes"
	},
	{
		"CategoryName": "Home & Garden > Business & Home Security > Security System Sensors"
	},
	{
		"CategoryName": "Home & Garden > Decor > Address Signs"
	},
	{
		"CategoryName": "Home & Garden > Decor > Artificial Flora"
	},
	{
		"CategoryName": "Home & Garden > Decor > Artificial Food"
	},
	{
		"CategoryName": "Home & Garden > Decor > Artwork > Decorative Tapestries"
	},
	{
		"CategoryName": "Home & Garden > Decor > Artwork > Posters, Prints, & Visual Artwork"
	},
	{
		"CategoryName": "Home & Garden > Decor > Artwork > Sculptures & Statues"
	},
	{
		"CategoryName": "Home & Garden > Decor > Backrest Pillows"
	},
	{
		"CategoryName": "Home & Garden > Decor > Baskets"
	},
	{
		"CategoryName": "Home & Garden > Decor > Bird & Wildlife Feeder Accessories"
	},
	{
		"CategoryName": "Home & Garden > Decor > Bird & Wildlife Feeders > Bird Feeders"
	},
	{
		"CategoryName": "Home & Garden > Decor > Bird & Wildlife Feeders > Butterfly Feeders"
	},
	{
		"CategoryName": "Home & Garden > Decor > Bird & Wildlife Feeders > Squirrel Feeders"
	},
	{
		"CategoryName": "Home & Garden > Decor > Bird & Wildlife House Accessories"
	},
	{
		"CategoryName": "Home & Garden > Decor > Bird & Wildlife Houses > Bat Houses"
	},
	{
		"CategoryName": "Home & Garden > Decor > Bird & Wildlife Houses > Birdhouses"
	},
	{
		"CategoryName": "Home & Garden > Decor > Bird & Wildlife Houses > Butterfly Houses"
	},
	{
		"CategoryName": "Home & Garden > Decor > Bird Baths"
	},
	{
		"CategoryName": "Home & Garden > Decor > Bookends"
	},
	{
		"CategoryName": "Home & Garden > Decor > Cardboard Cutouts"
	},
	{
		"CategoryName": "Home & Garden > Decor > Chair & Sofa Cushions"
	},
	{
		"CategoryName": "Home & Garden > Decor > Clock Parts"
	},
	{
		"CategoryName": "Home & Garden > Decor > Clocks > Alarm Clocks"
	},
	{
		"CategoryName": "Home & Garden > Decor > Clocks > Desk & Shelf Clocks"
	},
	{
		"CategoryName": "Home & Garden > Decor > Clocks > Floor & Grandfather Clocks"
	},
	{
		"CategoryName": "Home & Garden > Decor > Clocks > Wall Clocks"
	},
	{
		"CategoryName": "Home & Garden > Decor > Coat & Hat Racks"
	},
	{
		"CategoryName": "Home & Garden > Decor > Decorative Bells"
	},
	{
		"CategoryName": "Home & Garden > Decor > Decorative Bottles"
	},
	{
		"CategoryName": "Home & Garden > Decor > Decorative Bowls"
	},
	{
		"CategoryName": "Home & Garden > Decor > Decorative Jars"
	},
	{
		"CategoryName": "Home & Garden > Decor > Decorative Plaques"
	},
	{
		"CategoryName": "Home & Garden > Decor > Decorative Plates"
	},
	{
		"CategoryName": "Home & Garden > Decor > Decorative Trays"
	},
	{
		"CategoryName": "Home & Garden > Decor > Door Mats"
	},
	{
		"CategoryName": "Home & Garden > Decor > Dreamcatchers"
	},
	{
		"CategoryName": "Home & Garden > Decor > Dried Flowers"
	},
	{
		"CategoryName": "Home & Garden > Decor > Ecospheres"
	},
	{
		"CategoryName": "Home & Garden > Decor > Figurines"
	},
	{
		"CategoryName": "Home & Garden > Decor > Finials"
	},
	{
		"CategoryName": "Home & Garden > Decor > Flag & Windsock Accessories > Flag & Windsock Pole Lights"
	},
	{
		"CategoryName": "Home & Garden > Decor > Flag & Windsock Accessories > Flag & Windsock Pole Mounting Hardware & Kits"
	},
	{
		"CategoryName": "Home & Garden > Decor > Flag & Windsock Accessories > Flag & Windsock Poles"
	},
	{
		"CategoryName": "Home & Garden > Decor > Flags & Windsocks"
	},
	{
		"CategoryName": "Home & Garden > Decor > Flameless Candles"
	},
	{
		"CategoryName": "Home & Garden > Decor > Fountains & Ponds > Fountain & Pond Accessories"
	},
	{
		"CategoryName": "Home & Garden > Decor > Fountains & Ponds > Fountains & Waterfalls"
	},
	{
		"CategoryName": "Home & Garden > Decor > Fountains & Ponds > Ponds"
	},
	{
		"CategoryName": "Home & Garden > Decor > Garden & Stepping Stones"
	},
	{
		"CategoryName": "Home & Garden > Decor > Growth Charts"
	},
	{
		"CategoryName": "Home & Garden > Decor > Home Decor Decals"
	},
	{
		"CategoryName": "Home & Garden > Decor > Home Fragrance Accessories > Candle & Oil Warmers"
	},
	{
		"CategoryName": "Home & Garden > Decor > Home Fragrance Accessories > Candle Holders"
	},
	{
		"CategoryName": "Home & Garden > Decor > Home Fragrance Accessories > Candle Snuffers"
	},
	{
		"CategoryName": "Home & Garden > Decor > Home Fragrance Accessories > Incense Holders"
	},
	{
		"CategoryName": "Home & Garden > Decor > Home Fragrances > Air Fresheners"
	},
	{
		"CategoryName": "Home & Garden > Decor > Home Fragrances > Candles"
	},
	{
		"CategoryName": "Home & Garden > Decor > Home Fragrances > Fragrance Oil"
	},
	{
		"CategoryName": "Home & Garden > Decor > Home Fragrances > Incense"
	},
	{
		"CategoryName": "Home & Garden > Decor > Home Fragrances > Potpourri"
	},
	{
		"CategoryName": "Home & Garden > Decor > Home Fragrances > Wax Tarts"
	},
	{
		"CategoryName": "Home & Garden > Decor > Hourglasses"
	},
	{
		"CategoryName": "Home & Garden > Decor > House Numbers & Letters"
	},
	{
		"CategoryName": "Home & Garden > Decor > Lawn Ornaments & Garden Sculptures"
	},
	{
		"CategoryName": "Home & Garden > Decor > Mail Slots"
	},
	{
		"CategoryName": "Home & Garden > Decor > Mailbox Accessories > Mailbox Covers"
	},
	{
		"CategoryName": "Home & Garden > Decor > Mailbox Accessories > Mailbox Enclosures"
	},
	{
		"CategoryName": "Home & Garden > Decor > Mailbox Accessories > Mailbox Flags"
	},
	{
		"CategoryName": "Home & Garden > Decor > Mailbox Accessories > Mailbox Posts"
	},
	{
		"CategoryName": "Home & Garden > Decor > Mailbox Accessories > Mailbox Replacement Doors"
	},
	{
		"CategoryName": "Home & Garden > Decor > Mailboxes"
	},
	{
		"CategoryName": "Home & Garden > Decor > Mirrors"
	},
	{
		"CategoryName": "Home & Garden > Decor > Music Boxes"
	},
	{
		"CategoryName": "Home & Garden > Decor > Napkin Rings"
	},
	{
		"CategoryName": "Home & Garden > Decor > Novelty Signs"
	},
	{
		"CategoryName": "Home & Garden > Decor > Ottoman Cushions"
	},
	{
		"CategoryName": "Home & Garden > Decor > Picture Frames"
	},
	{
		"CategoryName": "Home & Garden > Decor > Piggy Banks & Money Jars"
	},
	{
		"CategoryName": "Home & Garden > Decor > Rain Chains"
	},
	{
		"CategoryName": "Home & Garden > Decor > Rain Gauges"
	},
	{
		"CategoryName": "Home & Garden > Decor > Refrigerator Magnets"
	},
	{
		"CategoryName": "Home & Garden > Decor > Rugs"
	},
	{
		"CategoryName": "Home & Garden > Decor > Seasonal & Holiday Decorations > Advent Calendars"
	},
	{
		"CategoryName": "Home & Garden > Decor > Seasonal & Holiday Decorations > Christmas Tree Skirts"
	},
	{
		"CategoryName": "Home & Garden > Decor > Seasonal & Holiday Decorations > Christmas Tree Stands"
	},
	{
		"CategoryName": "Home & Garden > Decor > Seasonal & Holiday Decorations > Easter Egg Decorating Kits"
	},
	{
		"CategoryName": "Home & Garden > Decor > Seasonal & Holiday Decorations > Holiday Ornament Displays & Stands"
	},
	{
		"CategoryName": "Home & Garden > Decor > Seasonal & Holiday Decorations > Holiday Ornament Hooks"
	},
	{
		"CategoryName": "Home & Garden > Decor > Seasonal & Holiday Decorations > Holiday Ornaments"
	},
	{
		"CategoryName": "Home & Garden > Decor > Seasonal & Holiday Decorations > Holiday Stocking Hangers"
	},
	{
		"CategoryName": "Home & Garden > Decor > Seasonal & Holiday Decorations > Holiday Stockings"
	},
	{
		"CategoryName": "Home & Garden > Decor > Seasonal & Holiday Decorations > Japanese Traditional Dolls"
	},
	{
		"CategoryName": "Home & Garden > Decor > Seasonal & Holiday Decorations > Nativity Sets"
	},
	{
		"CategoryName": "Home & Garden > Decor > Seasonal & Holiday Decorations > Seasonal Village Sets & Accessories"
	},
	{
		"CategoryName": "Home & Garden > Decor > Shadow Boxes"
	},
	{
		"CategoryName": "Home & Garden > Decor > Slipcovers"
	},
	{
		"CategoryName": "Home & Garden > Decor > Snow Globes"
	},
	{
		"CategoryName": "Home & Garden > Decor > Suncatchers"
	},
	{
		"CategoryName": "Home & Garden > Decor > Sundials"
	},
	{
		"CategoryName": "Home & Garden > Decor > Throw Pillows"
	},
	{
		"CategoryName": "Home & Garden > Decor > Trunks"
	},
	{
		"CategoryName": "Home & Garden > Decor > Vase Fillers & Table Scatters"
	},
	{
		"CategoryName": "Home & Garden > Decor > Vases"
	},
	{
		"CategoryName": "Home & Garden > Decor > Wallpaper"
	},
	{
		"CategoryName": "Home & Garden > Decor > Weather Vanes & Roof Decor"
	},
	{
		"CategoryName": "Home & Garden > Decor > Wind Chimes"
	},
	{
		"CategoryName": "Home & Garden > Decor > Wind Wheels & Spinners"
	},
	{
		"CategoryName": "Home & Garden > Decor > Window Magnets"
	},
	{
		"CategoryName": "Home & Garden > Decor > Window Treatment Accessories > Curtain & Drape Rings"
	},
	{
		"CategoryName": "Home & Garden > Decor > Window Treatment Accessories > Curtain & Drape Rods"
	},
	{
		"CategoryName": "Home & Garden > Decor > Window Treatment Accessories > Curtain Holdbacks & Tassels"
	},
	{
		"CategoryName": "Home & Garden > Decor > Window Treatment Accessories > Window Treatment Replacement Parts"
	},
	{
		"CategoryName": "Home & Garden > Decor > Window Treatments > Curtains & Drapes"
	},
	{
		"CategoryName": "Home & Garden > Decor > Window Treatments > Stained Glass Panels"
	},
	{
		"CategoryName": "Home & Garden > Decor > Window Treatments > Window Blinds & Shades"
	},
	{
		"CategoryName": "Home & Garden > Decor > Window Treatments > Window Films"
	},
	{
		"CategoryName": "Home & Garden > Decor > Window Treatments > Window Screens"
	},
	{
		"CategoryName": "Home & Garden > Decor > Window Treatments > Window Valances & Cornices"
	},
	{
		"CategoryName": "Home & Garden > Decor > World Globes"
	},
	{
		"CategoryName": "Home & Garden > Decor > Wreaths & Garlands"
	},
	{
		"CategoryName": "Home & Garden > Emergency Preparedness > Earthquake Alarms"
	},
	{
		"CategoryName": "Home & Garden > Emergency Preparedness > Emergency Blankets"
	},
	{
		"CategoryName": "Home & Garden > Emergency Preparedness > Emergency Food Kits"
	},
	{
		"CategoryName": "Home & Garden > Emergency Preparedness > Emergency Tools & Kits"
	},
	{
		"CategoryName": "Home & Garden > Emergency Preparedness > Furniture Anchors"
	},
	{
		"CategoryName": "Home & Garden > Fireplace & Wood Stove Accessories > Bellows"
	},
	{
		"CategoryName": "Home & Garden > Fireplace & Wood Stove Accessories > Fireplace & Wood Stove Grates"
	},
	{
		"CategoryName": "Home & Garden > Fireplace & Wood Stove Accessories > Fireplace Andirons"
	},
	{
		"CategoryName": "Home & Garden > Fireplace & Wood Stove Accessories > Fireplace Reflectors"
	},
	{
		"CategoryName": "Home & Garden > Fireplace & Wood Stove Accessories > Fireplace Screens"
	},
	{
		"CategoryName": "Home & Garden > Fireplace & Wood Stove Accessories > Fireplace Tools"
	},
	{
		"CategoryName": "Home & Garden > Fireplace & Wood Stove Accessories > Firewood & Fuel"
	},
	{
		"CategoryName": "Home & Garden > Fireplace & Wood Stove Accessories > Hearth Pads"
	},
	{
		"CategoryName": "Home & Garden > Fireplace & Wood Stove Accessories > Log Rack & Carrier Accessories"
	},
	{
		"CategoryName": "Home & Garden > Fireplace & Wood Stove Accessories > Log Racks & Carriers"
	},
	{
		"CategoryName": "Home & Garden > Fireplace & Wood Stove Accessories > Wood Stove Fans & Blowers"
	},
	{
		"CategoryName": "Home & Garden > Fireplaces"
	},
	{
		"CategoryName": "Home & Garden > Flood, Fire & Gas Safety > Fire Alarm Control Panels"
	},
	{
		"CategoryName": "Home & Garden > Flood, Fire & Gas Safety > Fire Alarms"
	},
	{
		"CategoryName": "Home & Garden > Flood, Fire & Gas Safety > Fire Extinguisher & Equipment Storage"
	},
	{
		"CategoryName": "Home & Garden > Flood, Fire & Gas Safety > Fire Extinguishers"
	},
	{
		"CategoryName": "Home & Garden > Flood, Fire & Gas Safety > Fire Sprinklers"
	},
	{
		"CategoryName": "Home & Garden > Flood, Fire & Gas Safety > Heat Detectors"
	},
	{
		"CategoryName": "Home & Garden > Flood, Fire & Gas Safety > Smoke & Carbon Monoxide Detectors"
	},
	{
		"CategoryName": "Home & Garden > Flood, Fire & Gas Safety > Water & Flood Detectors"
	},
	{
		"CategoryName": "Home & Garden > Household Appliance Accessories > Air Conditioner Accessories > Air Conditioner Covers"
	},
	{
		"CategoryName": "Home & Garden > Household Appliance Accessories > Air Conditioner Accessories > Air Conditioner Filters"
	},
	{
		"CategoryName": "Home & Garden > Household Appliance Accessories > Air Purifier Accessories > Air Purifier Filters"
	},
	{
		"CategoryName": "Home & Garden > Household Appliance Accessories > Dehumidifier Accessories"
	},
	{
		"CategoryName": "Home & Garden > Household Appliance Accessories > Fan Accessories"
	},
	{
		"CategoryName": "Home & Garden > Household Appliance Accessories > Floor & Steam Cleaner Accessories"
	},
	{
		"CategoryName": "Home & Garden > Household Appliance Accessories > Furnace & Boiler Accessories"
	},
	{
		"CategoryName": "Home & Garden > Household Appliance Accessories > Heating Radiator Accessories > Heating Radiator Reflectors"
	},
	{
		"CategoryName": "Home & Garden > Household Appliance Accessories > Humidifier Accessories > Humidifier Filters"
	},
	{
		"CategoryName": "Home & Garden > Household Appliance Accessories > Laundry Appliance Accessories > Garment Steamer Accessories"
	},
	{
		"CategoryName": "Home & Garden > Household Appliance Accessories > Laundry Appliance Accessories > Iron Accessories"
	},
	{
		"CategoryName": "Home & Garden > Household Appliance Accessories > Laundry Appliance Accessories > Steam Press Accessories"
	},
	{
		"CategoryName": "Home & Garden > Household Appliance Accessories > Laundry Appliance Accessories > Washer & Dryer Accessories"
	},
	{
		"CategoryName": "Home & Garden > Household Appliance Accessories > Patio Heater Accessories > Patio Heater Covers"
	},
	{
		"CategoryName": "Home & Garden > Household Appliance Accessories > Vacuum Accessories"
	},
	{
		"CategoryName": "Home & Garden > Household Appliance Accessories > Water Heater Accessories > Anode Rods"
	},
	{
		"CategoryName": "Home & Garden > Household Appliance Accessories > Water Heater Accessories > Hot Water Tanks"
	},
	{
		"CategoryName": "Home & Garden > Household Appliance Accessories > Water Heater Accessories > Water Heater Elements"
	},
	{
		"CategoryName": "Home & Garden > Household Appliance Accessories > Water Heater Accessories > Water Heater Expansion Tanks"
	},
	{
		"CategoryName": "Home & Garden > Household Appliance Accessories > Water Heater Accessories > Water Heater Pans"
	},
	{
		"CategoryName": "Home & Garden > Household Appliance Accessories > Water Heater Accessories > Water Heater Stacks"
	},
	{
		"CategoryName": "Home & Garden > Household Appliance Accessories > Water Heater Accessories > Water Heater Vents"
	},
	{
		"CategoryName": "Home & Garden > Household Appliances > Climate Control Appliances > Air Conditioners"
	},
	{
		"CategoryName": "Home & Garden > Household Appliances > Climate Control Appliances > Air Purifiers"
	},
	{
		"CategoryName": "Home & Garden > Household Appliances > Climate Control Appliances > Dehumidifiers"
	},
	{
		"CategoryName": "Home & Garden > Household Appliances > Climate Control Appliances > Duct Heaters"
	},
	{
		"CategoryName": "Home & Garden > Household Appliances > Climate Control Appliances > Evaporative Coolers"
	},
	{
		"CategoryName": "Home & Garden > Household Appliances > Climate Control Appliances > Fans > Ceiling Fans"
	},
	{
		"CategoryName": "Home & Garden > Household Appliances > Climate Control Appliances > Fans > Desk & Pedestal Fans"
	},
	{
		"CategoryName": "Home & Garden > Household Appliances > Climate Control Appliances > Fans > Powered Hand Fans & Misters"
	},
	{
		"CategoryName": "Home & Garden > Household Appliances > Climate Control Appliances > Fans > Ventilation Fans"
	},
	{
		"CategoryName": "Home & Garden > Household Appliances > Climate Control Appliances > Fans > Wall Mount Fans"
	},
	{
		"CategoryName": "Home & Garden > Household Appliances > Climate Control Appliances > Furnaces & Boilers"
	},
	{
		"CategoryName": "Home & Garden > Household Appliances > Climate Control Appliances > Heating Radiators"
	},
	{
		"CategoryName": "Home & Garden > Household Appliances > Climate Control Appliances > Humidifiers"
	},
	{
		"CategoryName": "Home & Garden > Household Appliances > Climate Control Appliances > Outdoor Misting Systems"
	},
	{
		"CategoryName": "Home & Garden > Household Appliances > Climate Control Appliances > Patio Heaters"
	},
	{
		"CategoryName": "Home & Garden > Household Appliances > Climate Control Appliances > Space Heaters"
	},
	{
		"CategoryName": "Home & Garden > Household Appliances > Floor & Carpet Dryers"
	},
	{
		"CategoryName": "Home & Garden > Household Appliances > Floor & Steam Cleaners"
	},
	{
		"CategoryName": "Home & Garden > Household Appliances > Floor Polishers & Buffers"
	},
	{
		"CategoryName": "Home & Garden > Household Appliances > Futon Dryers"
	},
	{
		"CategoryName": "Home & Garden > Household Appliances > Garage Door Keypads & Remotes"
	},
	{
		"CategoryName": "Home & Garden > Household Appliances > Garage Door Openers"
	},
	{
		"CategoryName": "Home & Garden > Household Appliances > Laundry Appliances > Dryers"
	},
	{
		"CategoryName": "Home & Garden > Household Appliances > Laundry Appliances > Garment Steamers"
	},
	{
		"CategoryName": "Home & Garden > Household Appliances > Laundry Appliances > Irons & Ironing Systems"
	},
	{
		"CategoryName": "Home & Garden > Household Appliances > Laundry Appliances > Laundry Combo Units"
	},
	{
		"CategoryName": "Home & Garden > Household Appliances > Laundry Appliances > Steam Presses"
	},
	{
		"CategoryName": "Home & Garden > Household Appliances > Laundry Appliances > Washing Machines"
	},
	{
		"CategoryName": "Home & Garden > Household Appliances > Ultrasonic Cleaners"
	},
	{
		"CategoryName": "Home & Garden > Household Appliances > Vacuums"
	},
	{
		"CategoryName": "Home & Garden > Household Appliances > Wallpaper Steamers"
	},
	{
		"CategoryName": "Home & Garden > Household Appliances > Water Heaters"
	},
	{
		"CategoryName": "Home & Garden > Household Supplies > Drawer & Shelf Liners"
	},
	{
		"CategoryName": "Home & Garden > Household Supplies > Floor Protection Films & Runners"
	},
	{
		"CategoryName": "Home & Garden > Household Supplies > Furniture Floor Protectors"
	},
	{
		"CategoryName": "Home & Garden > Household Supplies > Garage Floor Mats"
	},
	{
		"CategoryName": "Home & Garden > Household Supplies > Garbage Bags"
	},
	{
		"CategoryName": "Home & Garden > Household Supplies > Household Cleaning Supplies > Broom & Mop Handles"
	},
	{
		"CategoryName": "Home & Garden > Household Supplies > Household Cleaning Supplies > Broom Heads"
	},
	{
		"CategoryName": "Home & Garden > Household Supplies > Household Cleaning Supplies > Brooms"
	},
	{
		"CategoryName": "Home & Garden > Household Supplies > Household Cleaning Supplies > Buckets"
	},
	{
		"CategoryName": "Home & Garden > Household Supplies > Household Cleaning Supplies > Carpet Sweepers"
	},
	{
		"CategoryName": "Home & Garden > Household Supplies > Household Cleaning Supplies > Cleaning Gloves"
	},
	{
		"CategoryName": "Home & Garden > Household Supplies > Household Cleaning Supplies > Duster Refills"
	},
	{
		"CategoryName": "Home & Garden > Household Supplies > Household Cleaning Supplies > Dusters"
	},
	{
		"CategoryName": "Home & Garden > Household Supplies > Household Cleaning Supplies > Dustpans"
	},
	{
		"CategoryName": "Home & Garden > Household Supplies > Household Cleaning Supplies > Fabric & Upholstery Protectors"
	},
	{
		"CategoryName": "Home & Garden > Household Supplies > Household Cleaning Supplies > Household Cleaning Products > All-Purpose Cleaners"
	},
	{
		"CategoryName": "Home & Garden > Household Supplies > Household Cleaning Supplies > Household Cleaning Products > Carpet Cleaners"
	},
	{
		"CategoryName": "Home & Garden > Household Supplies > Household Cleaning Supplies > Household Cleaning Products > Descalers & Decalcifiers"
	},
	{
		"CategoryName": "Home & Garden > Household Supplies > Household Cleaning Supplies > Household Cleaning Products > Dish Detergent & Soap"
	},
	{
		"CategoryName": "Home & Garden > Household Supplies > Household Cleaning Supplies > Household Cleaning Products > Dishwasher Cleaners"
	},
	{
		"CategoryName": "Home & Garden > Household Supplies > Household Cleaning Supplies > Household Cleaning Products > Fabric & Upholstery Cleaners"
	},
	{
		"CategoryName": "Home & Garden > Household Supplies > Household Cleaning Supplies > Household Cleaning Products > Floor Cleaners"
	},
	{
		"CategoryName": "Home & Garden > Household Supplies > Household Cleaning Supplies > Household Cleaning Products > Furniture Cleaners & Polish"
	},
	{
		"CategoryName": "Home & Garden > Household Supplies > Household Cleaning Supplies > Household Cleaning Products > Glass & Surface Cleaners"
	},
	{
		"CategoryName": "Home & Garden > Household Supplies > Household Cleaning Supplies > Household Cleaning Products > Household Disinfectants"
	},
	{
		"CategoryName": "Home & Garden > Household Supplies > Household Cleaning Supplies > Household Cleaning Products > Oven & Grill Cleaners"
	},
	{
		"CategoryName": "Home & Garden > Household Supplies > Household Cleaning Supplies > Household Cleaning Products > Pet Odor & Stain Removers"
	},
	{
		"CategoryName": "Home & Garden > Household Supplies > Household Cleaning Supplies > Household Cleaning Products > Rinse Aids"
	},
	{
		"CategoryName": "Home & Garden > Household Supplies > Household Cleaning Supplies > Household Cleaning Products > Stainless Steel Cleaners & Polishes"
	},
	{
		"CategoryName": "Home & Garden > Household Supplies > Household Cleaning Supplies > Household Cleaning Products > Toilet Bowl Cleaners"
	},
	{
		"CategoryName": "Home & Garden > Household Supplies > Household Cleaning Supplies > Household Cleaning Products > Tub & Tile Cleaners"
	},
	{
		"CategoryName": "Home & Garden > Household Supplies > Household Cleaning Supplies > Household Cleaning Products > Washing Machine Cleaners"
	},
	{
		"CategoryName": "Home & Garden > Household Supplies > Household Cleaning Supplies > Mop Heads & Refills"
	},
	{
		"CategoryName": "Home & Garden > Household Supplies > Household Cleaning Supplies > Mops"
	},
	{
		"CategoryName": "Home & Garden > Household Supplies > Household Cleaning Supplies > Scrub Brush Heads & Refills"
	},
	{
		"CategoryName": "Home & Garden > Household Supplies > Household Cleaning Supplies > Scrub Brushes"
	},
	{
		"CategoryName": "Home & Garden > Household Supplies > Household Cleaning Supplies > Shop Towels & General-Purpose Cleaning Cloths"
	},
	{
		"CategoryName": "Home & Garden > Household Supplies > Household Cleaning Supplies > Sponges & Scouring Pads"
	},
	{
		"CategoryName": "Home & Garden > Household Supplies > Household Cleaning Supplies > Squeegees"
	},
	{
		"CategoryName": "Home & Garden > Household Supplies > Household Paper Products > Facial Tissues"
	},
	{
		"CategoryName": "Home & Garden > Household Supplies > Household Paper Products > Paper Napkins"
	},
	{
		"CategoryName": "Home & Garden > Household Supplies > Household Paper Products > Paper Towels"
	},
	{
		"CategoryName": "Home & Garden > Household Supplies > Household Paper Products > Toilet Paper"
	},
	{
		"CategoryName": "Home & Garden > Household Supplies > Household Thermometers"
	},
	{
		"CategoryName": "Home & Garden > Household Supplies > Laundry Supplies > Bleach"
	},
	{
		"CategoryName": "Home & Garden > Household Supplies > Laundry Supplies > Clothespins"
	},
	{
		"CategoryName": "Home & Garden > Household Supplies > Laundry Supplies > Dry Cleaning Kits"
	},
	{
		"CategoryName": "Home & Garden > Household Supplies > Laundry Supplies > Drying Racks & Hangers"
	},
	{
		"CategoryName": "Home & Garden > Household Supplies > Laundry Supplies > Fabric Refreshers"
	},
	{
		"CategoryName": "Home & Garden > Household Supplies > Laundry Supplies > Fabric Shavers"
	},
	{
		"CategoryName": "Home & Garden > Household Supplies > Laundry Supplies > Fabric Softeners & Dryer Sheets"
	},
	{
		"CategoryName": "Home & Garden > Household Supplies > Laundry Supplies > Fabric Stain Removers"
	},
	{
		"CategoryName": "Home & Garden > Household Supplies > Laundry Supplies > Fabric Starch"
	},
	{
		"CategoryName": "Home & Garden > Household Supplies > Laundry Supplies > Garment Shields"
	},
	{
		"CategoryName": "Home & Garden > Household Supplies > Laundry Supplies > Iron Rests"
	},
	{
		"CategoryName": "Home & Garden > Household Supplies > Laundry Supplies > Ironing Board Pads & Covers"
	},
	{
		"CategoryName": "Home & Garden > Household Supplies > Laundry Supplies > Ironing Board Replacement Parts"
	},
	{
		"CategoryName": "Home & Garden > Household Supplies > Laundry Supplies > Ironing Boards"
	},
	{
		"CategoryName": "Home & Garden > Household Supplies > Laundry Supplies > Laundry Balls"
	},
	{
		"CategoryName": "Home & Garden > Household Supplies > Laundry Supplies > Laundry Baskets"
	},
	{
		"CategoryName": "Home & Garden > Household Supplies > Laundry Supplies > Laundry Detergent"
	},
	{
		"CategoryName": "Home & Garden > Household Supplies > Laundry Supplies > Laundry Wash Bags & Frames"
	},
	{
		"CategoryName": "Home & Garden > Household Supplies > Laundry Supplies > Lint Rollers"
	},
	{
		"CategoryName": "Home & Garden > Household Supplies > Laundry Supplies > Wrinkle Releasers & Anti-Static Sprays"
	},
	{
		"CategoryName": "Home & Garden > Household Supplies > Moisture Absorbers"
	},
	{
		"CategoryName": "Home & Garden > Household Supplies > Pest Control > Fly Swatters"
	},
	{
		"CategoryName": "Home & Garden > Household Supplies > Pest Control > Pest Control Traps"
	},
	{
		"CategoryName": "Home & Garden > Household Supplies > Pest Control > Pesticides"
	},
	{
		"CategoryName": "Home & Garden > Household Supplies > Pest Control > Repellents"
	},
	{
		"CategoryName": "Home & Garden > Household Supplies > Pest Control > Repellents > Animal & Pet Repellents"
	},
	{
		"CategoryName": "Home & Garden > Household Supplies > Pest Control > Repellents > Household Insect Repellents"
	},
	{
		"CategoryName": "Home & Garden > Household Supplies > Rug Pads"
	},
	{
		"CategoryName": "Home & Garden > Household Supplies > Shoe Care & Tools > Boot Pulls"
	},
	{
		"CategoryName": "Home & Garden > Household Supplies > Shoe Care & Tools > Shoe Bags"
	},
	{
		"CategoryName": "Home & Garden > Household Supplies > Shoe Care & Tools > Shoe Brushes"
	},
	{
		"CategoryName": "Home & Garden > Household Supplies > Shoe Care & Tools > Shoe Care Kits"
	},
	{
		"CategoryName": "Home & Garden > Household Supplies > Shoe Care & Tools > Shoe Dryers"
	},
	{
		"CategoryName": "Home & Garden > Household Supplies > Shoe Care & Tools > Shoe Horns & Dressing Aids"
	},
	{
		"CategoryName": "Home & Garden > Household Supplies > Shoe Care & Tools > Shoe Polishers"
	},
	{
		"CategoryName": "Home & Garden > Household Supplies > Shoe Care & Tools > Shoe Polishes & Waxes"
	},
	{
		"CategoryName": "Home & Garden > Household Supplies > Shoe Care & Tools > Shoe Scrapers"
	},
	{
		"CategoryName": "Home & Garden > Household Supplies > Shoe Care & Tools > Shoe Treatments & Dyes"
	},
	{
		"CategoryName": "Home & Garden > Household Supplies > Shoe Care & Tools > Shoe Trees & Shapers"
	},
	{
		"CategoryName": "Home & Garden > Household Supplies > Stair Treads"
	},
	{
		"CategoryName": "Home & Garden > Household Supplies > Storage & Organization > Clothing & Closet Storage > Charging Valets"
	},
	{
		"CategoryName": "Home & Garden > Household Supplies > Storage & Organization > Clothing & Closet Storage > Closet Organizers & Garment Racks"
	},
	{
		"CategoryName": "Home & Garden > Household Supplies > Storage & Organization > Clothing & Closet Storage > Clothes Valets"
	},
	{
		"CategoryName": "Home & Garden > Household Supplies > Storage & Organization > Clothing & Closet Storage > Hangers"
	},
	{
		"CategoryName": "Home & Garden > Household Supplies > Storage & Organization > Clothing & Closet Storage > Hat Boxes"
	},
	{
		"CategoryName": "Home & Garden > Household Supplies > Storage & Organization > Clothing & Closet Storage > Shoe Racks & Organizers"
	},
	{
		"CategoryName": "Home & Garden > Household Supplies > Storage & Organization > Flatware Chests"
	},
	{
		"CategoryName": "Home & Garden > Household Supplies > Storage & Organization > Household Drawer Organizer Inserts"
	},
	{
		"CategoryName": "Home & Garden > Household Supplies > Storage & Organization > Household Storage Bags"
	},
	{
		"CategoryName": "Home & Garden > Household Supplies > Storage & Organization > Household Storage Caddies"
	},
	{
		"CategoryName": "Home & Garden > Household Supplies > Storage & Organization > Household Storage Containers"
	},
	{
		"CategoryName": "Home & Garden > Household Supplies > Storage & Organization > Household Storage Drawers"
	},
	{
		"CategoryName": "Home & Garden > Household Supplies > Storage & Organization > Photo Storage > Photo Albums"
	},
	{
		"CategoryName": "Home & Garden > Household Supplies > Storage & Organization > Photo Storage > Photo Storage Boxes"
	},
	{
		"CategoryName": "Home & Garden > Household Supplies > Storage & Organization > Storage Hooks & Racks > Ironing Board Hooks & Racks"
	},
	{
		"CategoryName": "Home & Garden > Household Supplies > Storage & Organization > Storage Hooks & Racks > Umbrella Stands & Racks"
	},
	{
		"CategoryName": "Home & Garden > Household Supplies > Storage & Organization > Storage Hooks & Racks > Utility Hooks"
	},
	{
		"CategoryName": "Home & Garden > Household Supplies > Trash Compactor Accessories"
	},
	{
		"CategoryName": "Home & Garden > Household Supplies > Waste Containment > Dumpsters"
	},
	{
		"CategoryName": "Home & Garden > Household Supplies > Waste Containment > Hazardous Waste Containers"
	},
	{
		"CategoryName": "Home & Garden > Household Supplies > Waste Containment > Recycling Containers"
	},
	{
		"CategoryName": "Home & Garden > Household Supplies > Waste Containment > Trash Cans & Wastebaskets"
	},
	{
		"CategoryName": "Home & Garden > Household Supplies > Waste Containment Accessories > Waste Container Carts"
	},
	{
		"CategoryName": "Home & Garden > Household Supplies > Waste Containment Accessories > Waste Container Enclosures"
	},
	{
		"CategoryName": "Home & Garden > Household Supplies > Waste Containment Accessories > Waste Container Labels & Signs"
	},
	{
		"CategoryName": "Home & Garden > Household Supplies > Waste Containment Accessories > Waste Container Lids"
	},
	{
		"CategoryName": "Home & Garden > Household Supplies > Waste Containment Accessories > Waste Container Wheels"
	},
	{
		"CategoryName": "Home & Garden > Kitchen & Dining > Barware > Absinthe Fountains"
	},
	{
		"CategoryName": "Home & Garden > Kitchen & Dining > Barware > Beer Dispensers & Taps"
	},
	{
		"CategoryName": "Home & Garden > Kitchen & Dining > Barware > Beverage Chilling Cubes & Sticks"
	},
	{
		"CategoryName": "Home & Garden > Kitchen & Dining > Barware > Beverage Tubs & Chillers"
	},
	{
		"CategoryName": "Home & Garden > Kitchen & Dining > Barware > Bottle Caps"
	},
	{
		"CategoryName": "Home & Garden > Kitchen & Dining > Barware > Bottle Stoppers & Savers"
	},
	{
		"CategoryName": "Home & Garden > Kitchen & Dining > Barware > Coaster Holders"
	},
	{
		"CategoryName": "Home & Garden > Kitchen & Dining > Barware > Coasters"
	},
	{
		"CategoryName": "Home & Garden > Kitchen & Dining > Barware > Cocktail & Barware Tool Sets"
	},
	{
		"CategoryName": "Home & Garden > Kitchen & Dining > Barware > Cocktail Shakers & Tools > Bar Ice Picks"
	},
	{
		"CategoryName": "Home & Garden > Kitchen & Dining > Barware > Cocktail Shakers & Tools > Bottle Openers"
	},
	{
		"CategoryName": "Home & Garden > Kitchen & Dining > Barware > Cocktail Shakers & Tools > Cocktail Shakers"
	},
	{
		"CategoryName": "Home & Garden > Kitchen & Dining > Barware > Cocktail Shakers & Tools > Cocktail Strainers"
	},
	{
		"CategoryName": "Home & Garden > Kitchen & Dining > Barware > Cocktail Shakers & Tools > Muddlers"
	},
	{
		"CategoryName": "Home & Garden > Kitchen & Dining > Barware > Corkscrews"
	},
	{
		"CategoryName": "Home & Garden > Kitchen & Dining > Barware > Decanters"
	},
	{
		"CategoryName": "Home & Garden > Kitchen & Dining > Barware > Foil Cutters"
	},
	{
		"CategoryName": "Home & Garden > Kitchen & Dining > Barware > Wine Aerators"
	},
	{
		"CategoryName": "Home & Garden > Kitchen & Dining > Barware > Wine Bottle Holders"
	},
	{
		"CategoryName": "Home & Garden > Kitchen & Dining > Barware > Wine Glass Charms"
	},
	{
		"CategoryName": "Home & Garden > Kitchen & Dining > Cookware & Bakeware > Bakeware > Bakeware Sets"
	},
	{
		"CategoryName": "Home & Garden > Kitchen & Dining > Cookware & Bakeware > Bakeware > Baking & Cookie Sheets"
	},
	{
		"CategoryName": "Home & Garden > Kitchen & Dining > Cookware & Bakeware > Bakeware > Bread Pans & Molds"
	},
	{
		"CategoryName": "Home & Garden > Kitchen & Dining > Cookware & Bakeware > Bakeware > Broiling Pans"
	},
	{
		"CategoryName": "Home & Garden > Kitchen & Dining > Cookware & Bakeware > Bakeware > Cake Pans & Molds"
	},
	{
		"CategoryName": "Home & Garden > Kitchen & Dining > Cookware & Bakeware > Bakeware > Muffin & Pastry Pans"
	},
	{
		"CategoryName": "Home & Garden > Kitchen & Dining > Cookware & Bakeware > Bakeware > Pie & Quiche Pans"
	},
	{
		"CategoryName": "Home & Garden > Kitchen & Dining > Cookware & Bakeware > Bakeware > Pizza Pans"
	},
	{
		"CategoryName": "Home & Garden > Kitchen & Dining > Cookware & Bakeware > Bakeware > Pizza Stones"
	},
	{
		"CategoryName": "Home & Garden > Kitchen & Dining > Cookware & Bakeware > Bakeware > Ramekins & Souffle Dishes"
	},
	{
		"CategoryName": "Home & Garden > Kitchen & Dining > Cookware & Bakeware > Bakeware > Roasting Pans"
	},
	{
		"CategoryName": "Home & Garden > Kitchen & Dining > Cookware & Bakeware > Bakeware Accessories > Baking Mats & Liners"
	},
	{
		"CategoryName": "Home & Garden > Kitchen & Dining > Cookware & Bakeware > Bakeware Accessories > Baking Weights"
	},
	{
		"CategoryName": "Home & Garden > Kitchen & Dining > Cookware & Bakeware > Bakeware Accessories > Roasting Pan Racks"
	},
	{
		"CategoryName": "Home & Garden > Kitchen & Dining > Cookware & Bakeware > Cookware & Bakeware Combo Sets"
	},
	{
		"CategoryName": "Home & Garden > Kitchen & Dining > Cookware & Bakeware > Cookware > Casserole Dishes"
	},
	{
		"CategoryName": "Home & Garden > Kitchen & Dining > Cookware & Bakeware > Cookware > Cookware Sets"
	},
	{
		"CategoryName": "Home & Garden > Kitchen & Dining > Cookware & Bakeware > Cookware > Crêpe & Blini Pans"
	},
	{
		"CategoryName": "Home & Garden > Kitchen & Dining > Cookware & Bakeware > Cookware > Double Boilers"
	},
	{
		"CategoryName": "Home & Garden > Kitchen & Dining > Cookware & Bakeware > Cookware > Dutch Ovens"
	},
	{
		"CategoryName": "Home & Garden > Kitchen & Dining > Cookware & Bakeware > Cookware > Fermentation & Pickling Crocks"
	},
	{
		"CategoryName": "Home & Garden > Kitchen & Dining > Cookware & Bakeware > Cookware > Griddles & Grill Pans"
	},
	{
		"CategoryName": "Home & Garden > Kitchen & Dining > Cookware & Bakeware > Cookware > Grill Presses"
	},
	{
		"CategoryName": "Home & Garden > Kitchen & Dining > Cookware & Bakeware > Cookware > Paella Pans"
	},
	{
		"CategoryName": "Home & Garden > Kitchen & Dining > Cookware & Bakeware > Cookware > Pressure Cookers & Canners"
	},
	{
		"CategoryName": "Home & Garden > Kitchen & Dining > Cookware & Bakeware > Cookware > Saucepans"
	},
	{
		"CategoryName": "Home & Garden > Kitchen & Dining > Cookware & Bakeware > Cookware > Sauté Pans"
	},
	{
		"CategoryName": "Home & Garden > Kitchen & Dining > Cookware & Bakeware > Cookware > Skillets & Frying Pans"
	},
	{
		"CategoryName": "Home & Garden > Kitchen & Dining > Cookware & Bakeware > Cookware > Stock Pots"
	},
	{
		"CategoryName": "Home & Garden > Kitchen & Dining > Cookware & Bakeware > Cookware > Stovetop Kettles"
	},
	{
		"CategoryName": "Home & Garden > Kitchen & Dining > Cookware & Bakeware > Cookware > Tagines & Clay Cooking Pots"
	},
	{
		"CategoryName": "Home & Garden > Kitchen & Dining > Cookware & Bakeware > Cookware > Woks"
	},
	{
		"CategoryName": "Home & Garden > Kitchen & Dining > Cookware & Bakeware > Cookware Accessories > Pot & Pan Handles"
	},
	{
		"CategoryName": "Home & Garden > Kitchen & Dining > Cookware & Bakeware > Cookware Accessories > Pot & Pan Lids"
	},
	{
		"CategoryName": "Home & Garden > Kitchen & Dining > Cookware & Bakeware > Cookware Accessories > Pressure Cooker & Canner Accessories"
	},
	{
		"CategoryName": "Home & Garden > Kitchen & Dining > Cookware & Bakeware > Cookware Accessories > Steamer Baskets"
	},
	{
		"CategoryName": "Home & Garden > Kitchen & Dining > Cookware & Bakeware > Cookware Accessories > Wok Accessories > Wok Brushes"
	},
	{
		"CategoryName": "Home & Garden > Kitchen & Dining > Cookware & Bakeware > Cookware Accessories > Wok Accessories > Wok Rings"
	},
	{
		"CategoryName": "Home & Garden > Kitchen & Dining > Food & Beverage Carriers > Airpots"
	},
	{
		"CategoryName": "Home & Garden > Kitchen & Dining > Food & Beverage Carriers > Canteens"
	},
	{
		"CategoryName": "Home & Garden > Kitchen & Dining > Food & Beverage Carriers > Coolers"
	},
	{
		"CategoryName": "Home & Garden > Kitchen & Dining > Food & Beverage Carriers > Drink Sleeves > Can & Bottle Sleeves"
	},
	{
		"CategoryName": "Home & Garden > Kitchen & Dining > Food & Beverage Carriers > Drink Sleeves > Cup Sleeves"
	},
	{
		"CategoryName": "Home & Garden > Kitchen & Dining > Food & Beverage Carriers > Flasks"
	},
	{
		"CategoryName": "Home & Garden > Kitchen & Dining > Food & Beverage Carriers > Insulated Bags"
	},
	{
		"CategoryName": "Home & Garden > Kitchen & Dining > Food & Beverage Carriers > Lunch Boxes & Totes"
	},
	{
		"CategoryName": "Home & Garden > Kitchen & Dining > Food & Beverage Carriers > Picnic Baskets"
	},
	{
		"CategoryName": "Home & Garden > Kitchen & Dining > Food & Beverage Carriers > Replacement Drink Lids"
	},
	{
		"CategoryName": "Home & Garden > Kitchen & Dining > Food & Beverage Carriers > Thermoses"
	},
	{
		"CategoryName": "Home & Garden > Kitchen & Dining > Food & Beverage Carriers > Water Bottles"
	},
	{
		"CategoryName": "Home & Garden > Kitchen & Dining > Food & Beverage Carriers > Wine Carrier Bags"
	},
	{
		"CategoryName": "Home & Garden > Kitchen & Dining > Food Storage > Bread Boxes & Bags"
	},
	{
		"CategoryName": "Home & Garden > Kitchen & Dining > Food Storage > Candy Buckets"
	},
	{
		"CategoryName": "Home & Garden > Kitchen & Dining > Food Storage > Cookie Jars"
	},
	{
		"CategoryName": "Home & Garden > Kitchen & Dining > Food Storage > Food Container Covers"
	},
	{
		"CategoryName": "Home & Garden > Kitchen & Dining > Food Storage > Food Storage Bags"
	},
	{
		"CategoryName": "Home & Garden > Kitchen & Dining > Food Storage > Food Storage Containers"
	},
	{
		"CategoryName": "Home & Garden > Kitchen & Dining > Food Storage > Food Wraps > Foil"
	},
	{
		"CategoryName": "Home & Garden > Kitchen & Dining > Food Storage > Food Wraps > Parchment Paper"
	},
	{
		"CategoryName": "Home & Garden > Kitchen & Dining > Food Storage > Food Wraps > Plastic Wrap"
	},
	{
		"CategoryName": "Home & Garden > Kitchen & Dining > Food Storage > Food Wraps > Wax Paper"
	},
	{
		"CategoryName": "Home & Garden > Kitchen & Dining > Food Storage > Honey Jars"
	},
	{
		"CategoryName": "Home & Garden > Kitchen & Dining > Food Storage Accessories > Food & Beverage Labels"
	},
	{
		"CategoryName": "Home & Garden > Kitchen & Dining > Food Storage Accessories > Food Wrap Dispensers"
	},
	{
		"CategoryName": "Home & Garden > Kitchen & Dining > Food Storage Accessories > Oxygen Absorbers"
	},
	{
		"CategoryName": "Home & Garden > Kitchen & Dining > Food Storage Accessories > Twist Ties & Bag Clips"
	},
	{
		"CategoryName": "Home & Garden > Kitchen & Dining > Kitchen Appliance Accessories > Breadmaker Accessories"
	},
	{
		"CategoryName": "Home & Garden > Kitchen & Dining > Kitchen Appliance Accessories > Coffee Maker & Espresso Machine Accessories > Coffee Decanter Warmers"
	},
	{
		"CategoryName": "Home & Garden > Kitchen & Dining > Kitchen Appliance Accessories > Coffee Maker & Espresso Machine Accessories > Coffee Decanters"
	},
	{
		"CategoryName": "Home & Garden > Kitchen & Dining > Kitchen Appliance Accessories > Coffee Maker & Espresso Machine Accessories > Coffee Filter Baskets"
	},
	{
		"CategoryName": "Home & Garden > Kitchen & Dining > Kitchen Appliance Accessories > Coffee Maker & Espresso Machine Accessories > Coffee Filters"
	},
	{
		"CategoryName": "Home & Garden > Kitchen & Dining > Kitchen Appliance Accessories > Coffee Maker & Espresso Machine Accessories > Coffee Grinder Accessories"
	},
	{
		"CategoryName": "Home & Garden > Kitchen & Dining > Kitchen Appliance Accessories > Coffee Maker & Espresso Machine Accessories > Coffee Grinders"
	},
	{
		"CategoryName": "Home & Garden > Kitchen & Dining > Kitchen Appliance Accessories > Coffee Maker & Espresso Machine Accessories > Coffee Maker & Espresso Machine Replacement Parts"
	},
	{
		"CategoryName": "Home & Garden > Kitchen & Dining > Kitchen Appliance Accessories > Coffee Maker & Espresso Machine Accessories > Coffee Maker Water Filters"
	},
	{
		"CategoryName": "Home & Garden > Kitchen & Dining > Kitchen Appliance Accessories > Coffee Maker & Espresso Machine Accessories > Frothing Pitchers"
	},
	{
		"CategoryName": "Home & Garden > Kitchen & Dining > Kitchen Appliance Accessories > Coffee Maker & Espresso Machine Accessories > Portafilters"
	},
	{
		"CategoryName": "Home & Garden > Kitchen & Dining > Kitchen Appliance Accessories > Cooktop, Oven & Range Accessories"
	},
	{
		"CategoryName": "Home & Garden > Kitchen & Dining > Kitchen Appliance Accessories > Cotton Candy Machine Accessories"
	},
	{
		"CategoryName": "Home & Garden > Kitchen & Dining > Kitchen Appliance Accessories > Deep Fryer Accessories"
	},
	{
		"CategoryName": "Home & Garden > Kitchen & Dining > Kitchen Appliance Accessories > Dishwasher Parts & Accessories"
	},
	{
		"CategoryName": "Home & Garden > Kitchen & Dining > Kitchen Appliance Accessories > Electric Kettle Accessories"
	},
	{
		"CategoryName": "Home & Garden > Kitchen & Dining > Kitchen Appliance Accessories > Electric Skillet & Wok Accessories"
	},
	{
		"CategoryName": "Home & Garden > Kitchen & Dining > Kitchen Appliance Accessories > Fondue Set Accessories > Cooking Gel Fuels"
	},
	{
		"CategoryName": "Home & Garden > Kitchen & Dining > Kitchen Appliance Accessories > Fondue Set Accessories > Fondue Forks"
	},
	{
		"CategoryName": "Home & Garden > Kitchen & Dining > Kitchen Appliance Accessories > Fondue Set Accessories > Fondue Pot Stands"
	},
	{
		"CategoryName": "Home & Garden > Kitchen & Dining > Kitchen Appliance Accessories > Food Dehydrator Accessories > Food Dehydrator Sheets"
	},
	{
		"CategoryName": "Home & Garden > Kitchen & Dining > Kitchen Appliance Accessories > Food Dehydrator Accessories > Food Dehydrator Trays"
	},
	{
		"CategoryName": "Home & Garden > Kitchen & Dining > Kitchen Appliance Accessories > Food Grinder Accessories"
	},
	{
		"CategoryName": "Home & Garden > Kitchen & Dining > Kitchen Appliance Accessories > Food Mixer & Blender Accessories"
	},
	{
		"CategoryName": "Home & Garden > Kitchen & Dining > Kitchen Appliance Accessories > Freezer Accessories"
	},
	{
		"CategoryName": "Home & Garden > Kitchen & Dining > Kitchen Appliance Accessories > Garbage Disposal Accessories"
	},
	{
		"CategoryName": "Home & Garden > Kitchen & Dining > Kitchen Appliance Accessories > Ice Cream Maker Accessories > Ice Cream Maker Freezer Bowls"
	},
	{
		"CategoryName": "Home & Garden > Kitchen & Dining > Kitchen Appliance Accessories > Ice Crusher & Shaver Accessories"
	},
	{
		"CategoryName": "Home & Garden > Kitchen & Dining > Kitchen Appliance Accessories > Ice Maker Accessories"
	},
	{
		"CategoryName": "Home & Garden > Kitchen & Dining > Kitchen Appliance Accessories > Juicer Accessories"
	},
	{
		"CategoryName": "Home & Garden > Kitchen & Dining > Kitchen Appliance Accessories > Microwave Oven Accessories"
	},
	{
		"CategoryName": "Home & Garden > Kitchen & Dining > Kitchen Appliance Accessories > Outdoor Grill Accessories > Charcoal Briquettes"
	},
	{
		"CategoryName": "Home & Garden > Kitchen & Dining > Kitchen Appliance Accessories > Outdoor Grill Accessories > Charcoal Chimneys"
	},
	{
		"CategoryName": "Home & Garden > Kitchen & Dining > Kitchen Appliance Accessories > Outdoor Grill Accessories > Outdoor Grill Carts"
	},
	{
		"CategoryName": "Home & Garden > Kitchen & Dining > Kitchen Appliance Accessories > Outdoor Grill Accessories > Outdoor Grill Covers"
	},
	{
		"CategoryName": "Home & Garden > Kitchen & Dining > Kitchen Appliance Accessories > Outdoor Grill Accessories > Outdoor Grill Racks & Toppers"
	},
	{
		"CategoryName": "Home & Garden > Kitchen & Dining > Kitchen Appliance Accessories > Outdoor Grill Accessories > Outdoor Grill Replacement Parts"
	},
	{
		"CategoryName": "Home & Garden > Kitchen & Dining > Kitchen Appliance Accessories > Outdoor Grill Accessories > Outdoor Grill Spits & Baskets"
	},
	{
		"CategoryName": "Home & Garden > Kitchen & Dining > Kitchen Appliance Accessories > Outdoor Grill Accessories > Outdoor Grilling Planks"
	},
	{
		"CategoryName": "Home & Garden > Kitchen & Dining > Kitchen Appliance Accessories > Outdoor Grill Accessories > Smoking Chips & Pellets"
	},
	{
		"CategoryName": "Home & Garden > Kitchen & Dining > Kitchen Appliance Accessories > Pasta Maker Accessories"
	},
	{
		"CategoryName": "Home & Garden > Kitchen & Dining > Kitchen Appliance Accessories > Popcorn Maker Accessories"
	},
	{
		"CategoryName": "Home & Garden > Kitchen & Dining > Kitchen Appliance Accessories > Portable Cooking Stove Accessories"
	},
	{
		"CategoryName": "Home & Garden > Kitchen & Dining > Kitchen Appliance Accessories > Range Hood Accessories"
	},
	{
		"CategoryName": "Home & Garden > Kitchen & Dining > Kitchen Appliance Accessories > Refrigerator Accessories"
	},
	{
		"CategoryName": "Home & Garden > Kitchen & Dining > Kitchen Appliance Accessories > Soda Maker Accessories"
	},
	{
		"CategoryName": "Home & Garden > Kitchen & Dining > Kitchen Appliance Accessories > Steam Table Accessories > Steam Table Pan Covers"
	},
	{
		"CategoryName": "Home & Garden > Kitchen & Dining > Kitchen Appliance Accessories > Steam Table Accessories > Steam Table Pans"
	},
	{
		"CategoryName": "Home & Garden > Kitchen & Dining > Kitchen Appliance Accessories > Toaster Accessories"
	},
	{
		"CategoryName": "Home & Garden > Kitchen & Dining > Kitchen Appliance Accessories > Vacuum Sealer Accessories > Vacuum Sealer Bags"
	},
	{
		"CategoryName": "Home & Garden > Kitchen & Dining > Kitchen Appliance Accessories > Waffle Iron Accessories"
	},
	{
		"CategoryName": "Home & Garden > Kitchen & Dining > Kitchen Appliance Accessories > Water Cooler Accessories > Water Cooler Bottles"
	},
	{
		"CategoryName": "Home & Garden > Kitchen & Dining > Kitchen Appliance Accessories > Wine Fridge Accessories"
	},
	{
		"CategoryName": "Home & Garden > Kitchen & Dining > Kitchen Appliance Accessories > Yogurt Maker Accessories"
	},
	{
		"CategoryName": "Home & Garden > Kitchen & Dining > Kitchen Appliances > Beverage Warmers"
	},
	{
		"CategoryName": "Home & Garden > Kitchen & Dining > Kitchen Appliances > Breadmakers"
	},
	{
		"CategoryName": "Home & Garden > Kitchen & Dining > Kitchen Appliances > Chocolate Tempering Machines"
	},
	{
		"CategoryName": "Home & Garden > Kitchen & Dining > Kitchen Appliances > Coffee Makers & Espresso Machines > Drip Coffee Makers"
	},
	{
		"CategoryName": "Home & Garden > Kitchen & Dining > Kitchen Appliances > Coffee Makers & Espresso Machines > Electric & Stovetop Espresso Pots"
	},
	{
		"CategoryName": "Home & Garden > Kitchen & Dining > Kitchen Appliances > Coffee Makers & Espresso Machines > Espresso Machines"
	},
	{
		"CategoryName": "Home & Garden > Kitchen & Dining > Kitchen Appliances > Coffee Makers & Espresso Machines > French Presses"
	},
	{
		"CategoryName": "Home & Garden > Kitchen & Dining > Kitchen Appliances > Coffee Makers & Espresso Machines > Percolators"
	},
	{
		"CategoryName": "Home & Garden > Kitchen & Dining > Kitchen Appliances > Coffee Makers & Espresso Machines > Vacuum Coffee Makers"
	},
	{
		"CategoryName": "Home & Garden > Kitchen & Dining > Kitchen Appliances > Cooktops"
	},
	{
		"CategoryName": "Home & Garden > Kitchen & Dining > Kitchen Appliances > Cotton Candy Machines"
	},
	{
		"CategoryName": "Home & Garden > Kitchen & Dining > Kitchen Appliances > Deep Fryers"
	},
	{
		"CategoryName": "Home & Garden > Kitchen & Dining > Kitchen Appliances > Deli Slicers"
	},
	{
		"CategoryName": "Home & Garden > Kitchen & Dining > Kitchen Appliances > Dishwashers"
	},
	{
		"CategoryName": "Home & Garden > Kitchen & Dining > Kitchen Appliances > Electric Griddles & Grills"
	},
	{
		"CategoryName": "Home & Garden > Kitchen & Dining > Kitchen Appliances > Electric Kettles"
	},
	{
		"CategoryName": "Home & Garden > Kitchen & Dining > Kitchen Appliances > Electric Skillets & Woks"
	},
	{
		"CategoryName": "Home & Garden > Kitchen & Dining > Kitchen Appliances > Fondue Pots & Sets"
	},
	{
		"CategoryName": "Home & Garden > Kitchen & Dining > Kitchen Appliances > Food Cookers & Steamers > Egg Cookers"
	},
	{
		"CategoryName": "Home & Garden > Kitchen & Dining > Kitchen Appliances > Food Cookers & Steamers > Food Steamers"
	},
	{
		"CategoryName": "Home & Garden > Kitchen & Dining > Kitchen Appliances > Food Cookers & Steamers > Rice Cookers"
	},
	{
		"CategoryName": "Home & Garden > Kitchen & Dining > Kitchen Appliances > Food Cookers & Steamers > Slow Cookers"
	},
	{
		"CategoryName": "Home & Garden > Kitchen & Dining > Kitchen Appliances > Food Cookers & Steamers > Thermal Cookers"
	},
	{
		"CategoryName": "Home & Garden > Kitchen & Dining > Kitchen Appliances > Food Cookers & Steamers > Water Ovens"
	},
	{
		"CategoryName": "Home & Garden > Kitchen & Dining > Kitchen Appliances > Food Dehydrators"
	},
	{
		"CategoryName": "Home & Garden > Kitchen & Dining > Kitchen Appliances > Food Grinders & Mills"
	},
	{
		"CategoryName": "Home & Garden > Kitchen & Dining > Kitchen Appliances > Food Mixers & Blenders"
	},
	{
		"CategoryName": "Home & Garden > Kitchen & Dining > Kitchen Appliances > Food Smokers"
	},
	{
		"CategoryName": "Home & Garden > Kitchen & Dining > Kitchen Appliances > Food Warmers > Chafing Dishes"
	},
	{
		"CategoryName": "Home & Garden > Kitchen & Dining > Kitchen Appliances > Food Warmers > Food Heat Lamps"
	},
	{
		"CategoryName": "Home & Garden > Kitchen & Dining > Kitchen Appliances > Food Warmers > Rice Keepers"
	},
	{
		"CategoryName": "Home & Garden > Kitchen & Dining > Kitchen Appliances > Food Warmers > Steam Tables"
	},
	{
		"CategoryName": "Home & Garden > Kitchen & Dining > Kitchen Appliances > Freezers"
	},
	{
		"CategoryName": "Home & Garden > Kitchen & Dining > Kitchen Appliances > Frozen Drink Makers"
	},
	{
		"CategoryName": "Home & Garden > Kitchen & Dining > Kitchen Appliances > Garbage Disposals"
	},
	{
		"CategoryName": "Home & Garden > Kitchen & Dining > Kitchen Appliances > Gas Griddles"
	},
	{
		"CategoryName": "Home & Garden > Kitchen & Dining > Kitchen Appliances > Hot Drink Makers"
	},
	{
		"CategoryName": "Home & Garden > Kitchen & Dining > Kitchen Appliances > Hot Plates"
	},
	{
		"CategoryName": "Home & Garden > Kitchen & Dining > Kitchen Appliances > Ice Cream Makers"
	},
	{
		"CategoryName": "Home & Garden > Kitchen & Dining > Kitchen Appliances > Ice Crushers & Shavers"
	},
	{
		"CategoryName": "Home & Garden > Kitchen & Dining > Kitchen Appliances > Ice Makers"
	},
	{
		"CategoryName": "Home & Garden > Kitchen & Dining > Kitchen Appliances > Juicers"
	},
	{
		"CategoryName": "Home & Garden > Kitchen & Dining > Kitchen Appliances > Knife Sharpeners"
	},
	{
		"CategoryName": "Home & Garden > Kitchen & Dining > Kitchen Appliances > Microwave Ovens"
	},
	{
		"CategoryName": "Home & Garden > Kitchen & Dining > Kitchen Appliances > Milk Frothers & Steamers"
	},
	{
		"CategoryName": "Home & Garden > Kitchen & Dining > Kitchen Appliances > Mochi Makers"
	},
	{
		"CategoryName": "Home & Garden > Kitchen & Dining > Kitchen Appliances > Outdoor Grills"
	},
	{
		"CategoryName": "Home & Garden > Kitchen & Dining > Kitchen Appliances > Ovens"
	},
	{
		"CategoryName": "Home & Garden > Kitchen & Dining > Kitchen Appliances > Pasta Makers"
	},
	{
		"CategoryName": "Home & Garden > Kitchen & Dining > Kitchen Appliances > Popcorn Makers"
	},
	{
		"CategoryName": "Home & Garden > Kitchen & Dining > Kitchen Appliances > Portable Cooking Stoves"
	},
	{
		"CategoryName": "Home & Garden > Kitchen & Dining > Kitchen Appliances > Range Hoods"
	},
	{
		"CategoryName": "Home & Garden > Kitchen & Dining > Kitchen Appliances > Ranges"
	},
	{
		"CategoryName": "Home & Garden > Kitchen & Dining > Kitchen Appliances > Refrigerators"
	},
	{
		"CategoryName": "Home & Garden > Kitchen & Dining > Kitchen Appliances > Roaster Ovens & Rotisseries"
	},
	{
		"CategoryName": "Home & Garden > Kitchen & Dining > Kitchen Appliances > Soda Makers"
	},
	{
		"CategoryName": "Home & Garden > Kitchen & Dining > Kitchen Appliances > Soy Milk Makers"
	},
	{
		"CategoryName": "Home & Garden > Kitchen & Dining > Kitchen Appliances > Tea Makers"
	},
	{
		"CategoryName": "Home & Garden > Kitchen & Dining > Kitchen Appliances > Toasters & Grills > Countertop & Toaster Ovens"
	},
	{
		"CategoryName": "Home & Garden > Kitchen & Dining > Kitchen Appliances > Toasters & Grills > Donut Makers"
	},
	{
		"CategoryName": "Home & Garden > Kitchen & Dining > Kitchen Appliances > Toasters & Grills > Muffin & Cupcake Makers"
	},
	{
		"CategoryName": "Home & Garden > Kitchen & Dining > Kitchen Appliances > Toasters & Grills > Pizza Makers & Ovens"
	},
	{
		"CategoryName": "Home & Garden > Kitchen & Dining > Kitchen Appliances > Toasters & Grills > Pizzelle Makers"
	},
	{
		"CategoryName": "Home & Garden > Kitchen & Dining > Kitchen Appliances > Toasters & Grills > Pretzel Makers"
	},
	{
		"CategoryName": "Home & Garden > Kitchen & Dining > Kitchen Appliances > Toasters & Grills > Sandwich Makers"
	},
	{
		"CategoryName": "Home & Garden > Kitchen & Dining > Kitchen Appliances > Toasters & Grills > Toasters"
	},
	{
		"CategoryName": "Home & Garden > Kitchen & Dining > Kitchen Appliances > Toasters & Grills > Tortilla & Flatbread Makers"
	},
	{
		"CategoryName": "Home & Garden > Kitchen & Dining > Kitchen Appliances > Toasters & Grills > Waffle Irons"
	},
	{
		"CategoryName": "Home & Garden > Kitchen & Dining > Kitchen Appliances > Trash Compactors"
	},
	{
		"CategoryName": "Home & Garden > Kitchen & Dining > Kitchen Appliances > Vacuum Sealers"
	},
	{
		"CategoryName": "Home & Garden > Kitchen & Dining > Kitchen Appliances > Water Coolers"
	},
	{
		"CategoryName": "Home & Garden > Kitchen & Dining > Kitchen Appliances > Water Filters"
	},
	{
		"CategoryName": "Home & Garden > Kitchen & Dining > Kitchen Appliances > Wine Fridges"
	},
	{
		"CategoryName": "Home & Garden > Kitchen & Dining > Kitchen Appliances > Yogurt Makers"
	},
	{
		"CategoryName": "Home & Garden > Kitchen & Dining > Kitchen Tools & Utensils > Aprons"
	},
	{
		"CategoryName": "Home & Garden > Kitchen & Dining > Kitchen Tools & Utensils > Baking Peels"
	},
	{
		"CategoryName": "Home & Garden > Kitchen & Dining > Kitchen Tools & Utensils > Basters"
	},
	{
		"CategoryName": "Home & Garden > Kitchen & Dining > Kitchen Tools & Utensils > Basting Brushes"
	},
	{
		"CategoryName": "Home & Garden > Kitchen & Dining > Kitchen Tools & Utensils > Beverage Dispensers"
	},
	{
		"CategoryName": "Home & Garden > Kitchen & Dining > Kitchen Tools & Utensils > Cake Decorating Supplies"
	},
	{
		"CategoryName": "Home & Garden > Kitchen & Dining > Kitchen Tools & Utensils > Cake Servers"
	},
	{
		"CategoryName": "Home & Garden > Kitchen & Dining > Kitchen Tools & Utensils > Can Crushers"
	},
	{
		"CategoryName": "Home & Garden > Kitchen & Dining > Kitchen Tools & Utensils > Can Openers"
	},
	{
		"CategoryName": "Home & Garden > Kitchen & Dining > Kitchen Tools & Utensils > Carving Forks"
	},
	{
		"CategoryName": "Home & Garden > Kitchen & Dining > Kitchen Tools & Utensils > Channel Knives"
	},
	{
		"CategoryName": "Home & Garden > Kitchen & Dining > Kitchen Tools & Utensils > Colanders & Strainers"
	},
	{
		"CategoryName": "Home & Garden > Kitchen & Dining > Kitchen Tools & Utensils > Condiment Dispensers"
	},
	{
		"CategoryName": "Home & Garden > Kitchen & Dining > Kitchen Tools & Utensils > Cookie Cutters"
	},
	{
		"CategoryName": "Home & Garden > Kitchen & Dining > Kitchen Tools & Utensils > Cookie Presses"
	},
	{
		"CategoryName": "Home & Garden > Kitchen & Dining > Kitchen Tools & Utensils > Cooking Thermometer Accessories"
	},
	{
		"CategoryName": "Home & Garden > Kitchen & Dining > Kitchen Tools & Utensils > Cooking Thermometers"
	},
	{
		"CategoryName": "Home & Garden > Kitchen & Dining > Kitchen Tools & Utensils > Cooking Timers"
	},
	{
		"CategoryName": "Home & Garden > Kitchen & Dining > Kitchen Tools & Utensils > Cooking Torches"
	},
	{
		"CategoryName": "Home & Garden > Kitchen & Dining > Kitchen Tools & Utensils > Cooling Racks"
	},
	{
		"CategoryName": "Home & Garden > Kitchen & Dining > Kitchen Tools & Utensils > Cutting Boards"
	},
	{
		"CategoryName": "Home & Garden > Kitchen & Dining > Kitchen Tools & Utensils > Dish Racks & Drain Boards"
	},
	{
		"CategoryName": "Home & Garden > Kitchen & Dining > Kitchen Tools & Utensils > Dough Wheels"
	},
	{
		"CategoryName": "Home & Garden > Kitchen & Dining > Kitchen Tools & Utensils > Electric Knife Accessories > Electric Knife Replacement Blades"
	},
	{
		"CategoryName": "Home & Garden > Kitchen & Dining > Kitchen Tools & Utensils > Electric Knives"
	},
	{
		"CategoryName": "Home & Garden > Kitchen & Dining > Kitchen Tools & Utensils > Flour Sifters"
	},
	{
		"CategoryName": "Home & Garden > Kitchen & Dining > Kitchen Tools & Utensils > Food & Drink Stencils"
	},
	{
		"CategoryName": "Home & Garden > Kitchen & Dining > Kitchen Tools & Utensils > Food Crackers > Lobster & Crab Crackers"
	},
	{
		"CategoryName": "Home & Garden > Kitchen & Dining > Kitchen Tools & Utensils > Food Crackers > Nutcrackers > Decorative Nutcrackers"
	},
	{
		"CategoryName": "Home & Garden > Kitchen & Dining > Kitchen Tools & Utensils > Food Dispensers"
	},
	{
		"CategoryName": "Home & Garden > Kitchen & Dining > Kitchen Tools & Utensils > Food Graters & Zesters"
	},
	{
		"CategoryName": "Home & Garden > Kitchen & Dining > Kitchen Tools & Utensils > Food Peelers & Corers"
	},
	{
		"CategoryName": "Home & Garden > Kitchen & Dining > Kitchen Tools & Utensils > Food Steaming Bags"
	},
	{
		"CategoryName": "Home & Garden > Kitchen & Dining > Kitchen Tools & Utensils > Food Sticks & Skewers"
	},
	{
		"CategoryName": "Home & Garden > Kitchen & Dining > Kitchen Tools & Utensils > Funnels"
	},
	{
		"CategoryName": "Home & Garden > Kitchen & Dining > Kitchen Tools & Utensils > Garlic Presses"
	},
	{
		"CategoryName": "Home & Garden > Kitchen & Dining > Kitchen Tools & Utensils > Gelatin Molds"
	},
	{
		"CategoryName": "Home & Garden > Kitchen & Dining > Kitchen Tools & Utensils > Ice Cube Trays"
	},
	{
		"CategoryName": "Home & Garden > Kitchen & Dining > Kitchen Tools & Utensils > Jerky Guns"
	},
	{
		"CategoryName": "Home & Garden > Kitchen & Dining > Kitchen Tools & Utensils > Kitchen Knives"
	},
	{
		"CategoryName": "Home & Garden > Kitchen & Dining > Kitchen Tools & Utensils > Kitchen Molds"
	},
	{
		"CategoryName": "Home & Garden > Kitchen & Dining > Kitchen Tools & Utensils > Kitchen Organizers > Can Organizers"
	},
	{
		"CategoryName": "Home & Garden > Kitchen & Dining > Kitchen Tools & Utensils > Kitchen Organizers > Drinkware Holders"
	},
	{
		"CategoryName": "Home & Garden > Kitchen & Dining > Kitchen Tools & Utensils > Kitchen Organizers > Kitchen Cabinet Organizers"
	},
	{
		"CategoryName": "Home & Garden > Kitchen & Dining > Kitchen Tools & Utensils > Kitchen Organizers > Kitchen Counter & Beverage Station Organizers"
	},
	{
		"CategoryName": "Home & Garden > Kitchen & Dining > Kitchen Tools & Utensils > Kitchen Organizers > Kitchen Utensil Holders & Racks"
	},
	{
		"CategoryName": "Home & Garden > Kitchen & Dining > Kitchen Tools & Utensils > Kitchen Organizers > Knife Blocks & Holders"
	},
	{
		"CategoryName": "Home & Garden > Kitchen & Dining > Kitchen Tools & Utensils > Kitchen Organizers > Napkin Holders & Dispensers"
	},
	{
		"CategoryName": "Home & Garden > Kitchen & Dining > Kitchen Tools & Utensils > Kitchen Organizers > Paper Towel Holders & Dispensers"
	},
	{
		"CategoryName": "Home & Garden > Kitchen & Dining > Kitchen Tools & Utensils > Kitchen Organizers > Pot Racks"
	},
	{
		"CategoryName": "Home & Garden > Kitchen & Dining > Kitchen Tools & Utensils > Kitchen Organizers > Spice Organizers"
	},
	{
		"CategoryName": "Home & Garden > Kitchen & Dining > Kitchen Tools & Utensils > Kitchen Organizers > Straw Holders & Dispensers"
	},
	{
		"CategoryName": "Home & Garden > Kitchen & Dining > Kitchen Tools & Utensils > Kitchen Organizers > Sugar Caddies"
	},
	{
		"CategoryName": "Home & Garden > Kitchen & Dining > Kitchen Tools & Utensils > Kitchen Organizers > Toothpick Holders & Dispensers"
	},
	{
		"CategoryName": "Home & Garden > Kitchen & Dining > Kitchen Tools & Utensils > Kitchen Organizers > Utensil & Flatware Trays"
	},
	{
		"CategoryName": "Home & Garden > Kitchen & Dining > Kitchen Tools & Utensils > Kitchen Scrapers > Bench Scrapers"
	},
	{
		"CategoryName": "Home & Garden > Kitchen & Dining > Kitchen Tools & Utensils > Kitchen Scrapers > Bowl Scrapers"
	},
	{
		"CategoryName": "Home & Garden > Kitchen & Dining > Kitchen Tools & Utensils > Kitchen Scrapers > Grill Scrapers"
	},
	{
		"CategoryName": "Home & Garden > Kitchen & Dining > Kitchen Tools & Utensils > Kitchen Shears"
	},
	{
		"CategoryName": "Home & Garden > Kitchen & Dining > Kitchen Tools & Utensils > Kitchen Slicers"
	},
	{
		"CategoryName": "Home & Garden > Kitchen & Dining > Kitchen Tools & Utensils > Kitchen Utensil Sets"
	},
	{
		"CategoryName": "Home & Garden > Kitchen & Dining > Kitchen Tools & Utensils > Ladles"
	},
	{
		"CategoryName": "Home & Garden > Kitchen & Dining > Kitchen Tools & Utensils > Mashers"
	},
	{
		"CategoryName": "Home & Garden > Kitchen & Dining > Kitchen Tools & Utensils > Measuring Cups & Spoons"
	},
	{
		"CategoryName": "Home & Garden > Kitchen & Dining > Kitchen Tools & Utensils > Meat Tenderizers"
	},
	{
		"CategoryName": "Home & Garden > Kitchen & Dining > Kitchen Tools & Utensils > Mixing Bowls"
	},
	{
		"CategoryName": "Home & Garden > Kitchen & Dining > Kitchen Tools & Utensils > Mortars & Pestles"
	},
	{
		"CategoryName": "Home & Garden > Kitchen & Dining > Kitchen Tools & Utensils > Oil & Vinegar Dispensers"
	},
	{
		"CategoryName": "Home & Garden > Kitchen & Dining > Kitchen Tools & Utensils > Oven Bags"
	},
	{
		"CategoryName": "Home & Garden > Kitchen & Dining > Kitchen Tools & Utensils > Oven Mitts & Pot Holders"
	},
	{
		"CategoryName": "Home & Garden > Kitchen & Dining > Kitchen Tools & Utensils > Pasta Molds & Stamps"
	},
	{
		"CategoryName": "Home & Garden > Kitchen & Dining > Kitchen Tools & Utensils > Pastry Blenders"
	},
	{
		"CategoryName": "Home & Garden > Kitchen & Dining > Kitchen Tools & Utensils > Pastry Cloths"
	},
	{
		"CategoryName": "Home & Garden > Kitchen & Dining > Kitchen Tools & Utensils > Pizza Cutter Accessories"
	},
	{
		"CategoryName": "Home & Garden > Kitchen & Dining > Kitchen Tools & Utensils > Pizza Cutters"
	},
	{
		"CategoryName": "Home & Garden > Kitchen & Dining > Kitchen Tools & Utensils > Ricers"
	},
	{
		"CategoryName": "Home & Garden > Kitchen & Dining > Kitchen Tools & Utensils > Rolling Pin Accessories > Rolling Pin Covers & Sleeves"
	},
	{
		"CategoryName": "Home & Garden > Kitchen & Dining > Kitchen Tools & Utensils > Rolling Pin Accessories > Rolling Pin Rings"
	},
	{
		"CategoryName": "Home & Garden > Kitchen & Dining > Kitchen Tools & Utensils > Rolling Pins"
	},
	{
		"CategoryName": "Home & Garden > Kitchen & Dining > Kitchen Tools & Utensils > Salad Dressing Mixers & Shakers"
	},
	{
		"CategoryName": "Home & Garden > Kitchen & Dining > Kitchen Tools & Utensils > Salad Spinners"
	},
	{
		"CategoryName": "Home & Garden > Kitchen & Dining > Kitchen Tools & Utensils > Scoops > Ice Cream Scoops"
	},
	{
		"CategoryName": "Home & Garden > Kitchen & Dining > Kitchen Tools & Utensils > Scoops > Ice Scoops"
	},
	{
		"CategoryName": "Home & Garden > Kitchen & Dining > Kitchen Tools & Utensils > Scoops > Melon Ballers"
	},
	{
		"CategoryName": "Home & Garden > Kitchen & Dining > Kitchen Tools & Utensils > Scoops > Popcorn & French Fry Scoops"
	},
	{
		"CategoryName": "Home & Garden > Kitchen & Dining > Kitchen Tools & Utensils > Sink Caddies"
	},
	{
		"CategoryName": "Home & Garden > Kitchen & Dining > Kitchen Tools & Utensils > Sink Mats & Grids"
	},
	{
		"CategoryName": "Home & Garden > Kitchen & Dining > Kitchen Tools & Utensils > Slotted Spoons"
	},
	{
		"CategoryName": "Home & Garden > Kitchen & Dining > Kitchen Tools & Utensils > Spatulas"
	},
	{
		"CategoryName": "Home & Garden > Kitchen & Dining > Kitchen Tools & Utensils > Spice Grinder Accessories"
	},
	{
		"CategoryName": "Home & Garden > Kitchen & Dining > Kitchen Tools & Utensils > Spice Grinders"
	},
	{
		"CategoryName": "Home & Garden > Kitchen & Dining > Kitchen Tools & Utensils > Spoon Rests"
	},
	{
		"CategoryName": "Home & Garden > Kitchen & Dining > Kitchen Tools & Utensils > Sugar Dispensers"
	},
	{
		"CategoryName": "Home & Garden > Kitchen & Dining > Kitchen Tools & Utensils > Sushi Mats"
	},
	{
		"CategoryName": "Home & Garden > Kitchen & Dining > Kitchen Tools & Utensils > Tea Strainers"
	},
	{
		"CategoryName": "Home & Garden > Kitchen & Dining > Kitchen Tools & Utensils > Tongs"
	},
	{
		"CategoryName": "Home & Garden > Kitchen & Dining > Kitchen Tools & Utensils > Whisks"
	},
	{
		"CategoryName": "Home & Garden > Kitchen & Dining > Prefabricated Kitchens & Kitchenettes"
	},
	{
		"CategoryName": "Home & Garden > Kitchen & Dining > Tableware > Coffee & Tea Sets"
	},
	{
		"CategoryName": "Home & Garden > Kitchen & Dining > Tableware > Coffee Servers & Tea Pots"
	},
	{
		"CategoryName": "Home & Garden > Kitchen & Dining > Tableware > Dinnerware > Bowls"
	},
	{
		"CategoryName": "Home & Garden > Kitchen & Dining > Tableware > Dinnerware > Dinnerware Sets"
	},
	{
		"CategoryName": "Home & Garden > Kitchen & Dining > Tableware > Dinnerware > Plates"
	},
	{
		"CategoryName": "Home & Garden > Kitchen & Dining > Tableware > Drinkware > Beer Glasses"
	},
	{
		"CategoryName": "Home & Garden > Kitchen & Dining > Tableware > Drinkware > Coffee & Tea Cups"
	},
	{
		"CategoryName": "Home & Garden > Kitchen & Dining > Tableware > Drinkware > Coffee & Tea Saucers"
	},
	{
		"CategoryName": "Home & Garden > Kitchen & Dining > Tableware > Drinkware > Drinkware Sets"
	},
	{
		"CategoryName": "Home & Garden > Kitchen & Dining > Tableware > Drinkware > Mugs"
	},
	{
		"CategoryName": "Home & Garden > Kitchen & Dining > Tableware > Drinkware > Shot Glasses"
	},
	{
		"CategoryName": "Home & Garden > Kitchen & Dining > Tableware > Drinkware > Stemware"
	},
	{
		"CategoryName": "Home & Garden > Kitchen & Dining > Tableware > Drinkware > Tumblers"
	},
	{
		"CategoryName": "Home & Garden > Kitchen & Dining > Tableware > Flatware > Chopstick Accessories"
	},
	{
		"CategoryName": "Home & Garden > Kitchen & Dining > Tableware > Flatware > Chopsticks"
	},
	{
		"CategoryName": "Home & Garden > Kitchen & Dining > Tableware > Flatware > Flatware Sets"
	},
	{
		"CategoryName": "Home & Garden > Kitchen & Dining > Tableware > Flatware > Forks"
	},
	{
		"CategoryName": "Home & Garden > Kitchen & Dining > Tableware > Flatware > Spoons"
	},
	{
		"CategoryName": "Home & Garden > Kitchen & Dining > Tableware > Flatware > Table Knives"
	},
	{
		"CategoryName": "Home & Garden > Kitchen & Dining > Tableware > Salt & Pepper Shakers"
	},
	{
		"CategoryName": "Home & Garden > Kitchen & Dining > Tableware > Serveware > Butter Dishes"
	},
	{
		"CategoryName": "Home & Garden > Kitchen & Dining > Tableware > Serveware > Cake Boards"
	},
	{
		"CategoryName": "Home & Garden > Kitchen & Dining > Tableware > Serveware > Cake Stands"
	},
	{
		"CategoryName": "Home & Garden > Kitchen & Dining > Tableware > Serveware > Egg Cups"
	},
	{
		"CategoryName": "Home & Garden > Kitchen & Dining > Tableware > Serveware > Gravy Boats"
	},
	{
		"CategoryName": "Home & Garden > Kitchen & Dining > Tableware > Serveware > Punch Bowls"
	},
	{
		"CategoryName": "Home & Garden > Kitchen & Dining > Tableware > Serveware > Serving Pitchers & Carafes"
	},
	{
		"CategoryName": "Home & Garden > Kitchen & Dining > Tableware > Serveware > Serving Platters"
	},
	{
		"CategoryName": "Home & Garden > Kitchen & Dining > Tableware > Serveware > Serving Trays"
	},
	{
		"CategoryName": "Home & Garden > Kitchen & Dining > Tableware > Serveware > Sugar Bowls & Creamers"
	},
	{
		"CategoryName": "Home & Garden > Kitchen & Dining > Tableware > Serveware > Tureens"
	},
	{
		"CategoryName": "Home & Garden > Kitchen & Dining > Tableware > Serveware Accessories > Punch Bowl Stands"
	},
	{
		"CategoryName": "Home & Garden > Kitchen & Dining > Tableware > Serveware Accessories > Tureen Lids"
	},
	{
		"CategoryName": "Home & Garden > Kitchen & Dining > Tableware > Serveware Accessories > Tureen Stands"
	},
	{
		"CategoryName": "Home & Garden > Kitchen & Dining > Tableware > Tablecloth Clips & Weights"
	},
	{
		"CategoryName": "Home & Garden > Kitchen & Dining > Tableware > Trivets"
	},
	{
		"CategoryName": "Home & Garden > Lawn & Garden > Gardening > Composting > Compost"
	},
	{
		"CategoryName": "Home & Garden > Lawn & Garden > Gardening > Composting > Compost Aerators"
	},
	{
		"CategoryName": "Home & Garden > Lawn & Garden > Gardening > Composting > Composters"
	},
	{
		"CategoryName": "Home & Garden > Lawn & Garden > Gardening > Disease Control"
	},
	{
		"CategoryName": "Home & Garden > Lawn & Garden > Gardening > Fertilizers"
	},
	{
		"CategoryName": "Home & Garden > Lawn & Garden > Gardening > Garden Pot Saucers & Trays"
	},
	{
		"CategoryName": "Home & Garden > Lawn & Garden > Gardening > Gardening Accessories > Gardening Scooters, Seats & Kneelers"
	},
	{
		"CategoryName": "Home & Garden > Lawn & Garden > Gardening > Gardening Accessories > Gardening Totes"
	},
	{
		"CategoryName": "Home & Garden > Lawn & Garden > Gardening > Gardening Accessories > Potting Benches"
	},
	{
		"CategoryName": "Home & Garden > Lawn & Garden > Gardening > Gardening Tool Accessories > Gardening Tool Handles"
	},
	{
		"CategoryName": "Home & Garden > Lawn & Garden > Gardening > Gardening Tool Accessories > Gardening Tool Heads"
	},
	{
		"CategoryName": "Home & Garden > Lawn & Garden > Gardening > Gardening Tool Accessories > Wheelbarrow Parts"
	},
	{
		"CategoryName": "Home & Garden > Lawn & Garden > Gardening > Gardening Tools > Bulb Planting Tools"
	},
	{
		"CategoryName": "Home & Garden > Lawn & Garden > Gardening > Gardening Tools > Cultivating Tools"
	},
	{
		"CategoryName": "Home & Garden > Lawn & Garden > Gardening > Gardening Tools > Gardening Forks"
	},
	{
		"CategoryName": "Home & Garden > Lawn & Garden > Gardening > Gardening Tools > Gardening Sickles & Machetes"
	},
	{
		"CategoryName": "Home & Garden > Lawn & Garden > Gardening > Gardening Tools > Gardening Trowels"
	},
	{
		"CategoryName": "Home & Garden > Lawn & Garden > Gardening > Gardening Tools > Lawn & Garden Sprayers"
	},
	{
		"CategoryName": "Home & Garden > Lawn & Garden > Gardening > Gardening Tools > Lawn Rollers"
	},
	{
		"CategoryName": "Home & Garden > Lawn & Garden > Gardening > Gardening Tools > Pruning Saws"
	},
	{
		"CategoryName": "Home & Garden > Lawn & Garden > Gardening > Gardening Tools > Pruning Shears"
	},
	{
		"CategoryName": "Home & Garden > Lawn & Garden > Gardening > Gardening Tools > Rakes"
	},
	{
		"CategoryName": "Home & Garden > Lawn & Garden > Gardening > Gardening Tools > Shovels & Spades"
	},
	{
		"CategoryName": "Home & Garden > Lawn & Garden > Gardening > Gardening Tools > Spreaders"
	},
	{
		"CategoryName": "Home & Garden > Lawn & Garden > Gardening > Gardening Tools > Wheelbarrows"
	},
	{
		"CategoryName": "Home & Garden > Lawn & Garden > Gardening > Greenhouses"
	},
	{
		"CategoryName": "Home & Garden > Lawn & Garden > Gardening > Herbicides"
	},
	{
		"CategoryName": "Home & Garden > Lawn & Garden > Gardening > Landscape Fabric"
	},
	{
		"CategoryName": "Home & Garden > Lawn & Garden > Gardening > Landscape Fabric Accessories > Landscape Fabric Staples & Pins"
	},
	{
		"CategoryName": "Home & Garden > Lawn & Garden > Gardening > Landscape Fabric Accessories > Landscape Fabric Tape"
	},
	{
		"CategoryName": "Home & Garden > Lawn & Garden > Gardening > Mulch"
	},
	{
		"CategoryName": "Home & Garden > Lawn & Garden > Gardening > Plant Cages & Supports"
	},
	{
		"CategoryName": "Home & Garden > Lawn & Garden > Gardening > Plant Stands"
	},
	{
		"CategoryName": "Home & Garden > Lawn & Garden > Gardening > Pot & Planter Liners"
	},
	{
		"CategoryName": "Home & Garden > Lawn & Garden > Gardening > Pots & Planters"
	},
	{
		"CategoryName": "Home & Garden > Lawn & Garden > Gardening > Rain Barrels"
	},
	{
		"CategoryName": "Home & Garden > Lawn & Garden > Gardening > Sands & Soils"
	},
	{
		"CategoryName": "Home & Garden > Lawn & Garden > Outdoor Living > Awning Accessories"
	},
	{
		"CategoryName": "Home & Garden > Lawn & Garden > Outdoor Living > Awnings"
	},
	{
		"CategoryName": "Home & Garden > Lawn & Garden > Outdoor Living > Hammock Parts & Accessories"
	},
	{
		"CategoryName": "Home & Garden > Lawn & Garden > Outdoor Living > Hammocks"
	},
	{
		"CategoryName": "Home & Garden > Lawn & Garden > Outdoor Living > Outdoor Blankets > Beach Mats"
	},
	{
		"CategoryName": "Home & Garden > Lawn & Garden > Outdoor Living > Outdoor Blankets > Picnic Blankets"
	},
	{
		"CategoryName": "Home & Garden > Lawn & Garden > Outdoor Living > Outdoor Blankets > Poncho Liners"
	},
	{
		"CategoryName": "Home & Garden > Lawn & Garden > Outdoor Living > Outdoor Structures > Canopies & Gazebos"
	},
	{
		"CategoryName": "Home & Garden > Lawn & Garden > Outdoor Living > Outdoor Structures > Canopy & Gazebo Accessories > Canopy & Gazebo Enclosure Kits"
	},
	{
		"CategoryName": "Home & Garden > Lawn & Garden > Outdoor Living > Outdoor Structures > Canopy & Gazebo Accessories > Canopy & Gazebo Frames"
	},
	{
		"CategoryName": "Home & Garden > Lawn & Garden > Outdoor Living > Outdoor Structures > Canopy & Gazebo Accessories > Canopy & Gazebo Tops"
	},
	{
		"CategoryName": "Home & Garden > Lawn & Garden > Outdoor Living > Outdoor Structures > Canopy & Gazebo Accessories > Canopy Poles"
	},
	{
		"CategoryName": "Home & Garden > Lawn & Garden > Outdoor Living > Outdoor Structures > Canopy & Gazebo Accessories > Canopy Weights"
	},
	{
		"CategoryName": "Home & Garden > Lawn & Garden > Outdoor Living > Outdoor Structures > Garden Arches, Trellises, Arbors & Pergolas"
	},
	{
		"CategoryName": "Home & Garden > Lawn & Garden > Outdoor Living > Outdoor Structures > Garden Bridges"
	},
	{
		"CategoryName": "Home & Garden > Lawn & Garden > Outdoor Living > Outdoor Structures > Sheds, Garages & Carports"
	},
	{
		"CategoryName": "Home & Garden > Lawn & Garden > Outdoor Living > Outdoor Umbrella & Sunshade Accessories > Outdoor Umbrella & Sunshade Fabric"
	},
	{
		"CategoryName": "Home & Garden > Lawn & Garden > Outdoor Living > Outdoor Umbrella & Sunshade Accessories > Outdoor Umbrella Bases"
	},
	{
		"CategoryName": "Home & Garden > Lawn & Garden > Outdoor Living > Outdoor Umbrella & Sunshade Accessories > Outdoor Umbrella Covers"
	},
	{
		"CategoryName": "Home & Garden > Lawn & Garden > Outdoor Living > Outdoor Umbrella & Sunshade Accessories > Outdoor Umbrella Enclosure Kits"
	},
	{
		"CategoryName": "Home & Garden > Lawn & Garden > Outdoor Living > Outdoor Umbrella & Sunshade Accessories > Outdoor Umbrella Lights"
	},
	{
		"CategoryName": "Home & Garden > Lawn & Garden > Outdoor Living > Outdoor Umbrellas & Sunshades"
	},
	{
		"CategoryName": "Home & Garden > Lawn & Garden > Outdoor Living > Porch Swing Accessories"
	},
	{
		"CategoryName": "Home & Garden > Lawn & Garden > Outdoor Living > Porch Swings"
	},
	{
		"CategoryName": "Home & Garden > Lawn & Garden > Outdoor Power Equipment > Chainsaws"
	},
	{
		"CategoryName": "Home & Garden > Lawn & Garden > Outdoor Power Equipment > Grass Edgers"
	},
	{
		"CategoryName": "Home & Garden > Lawn & Garden > Outdoor Power Equipment > Hedge Trimmers"
	},
	{
		"CategoryName": "Home & Garden > Lawn & Garden > Outdoor Power Equipment > Lawn Aerators & Dethatchers"
	},
	{
		"CategoryName": "Home & Garden > Lawn & Garden > Outdoor Power Equipment > Lawn Mowers > Riding Mowers"
	},
	{
		"CategoryName": "Home & Garden > Lawn & Garden > Outdoor Power Equipment > Lawn Mowers > Robotic Mowers"
	},
	{
		"CategoryName": "Home & Garden > Lawn & Garden > Outdoor Power Equipment > Lawn Mowers > Tow-Behind Mowers"
	},
	{
		"CategoryName": "Home & Garden > Lawn & Garden > Outdoor Power Equipment > Lawn Mowers > Walk-Behind Mowers"
	},
	{
		"CategoryName": "Home & Garden > Lawn & Garden > Outdoor Power Equipment > Lawn Vacuums"
	},
	{
		"CategoryName": "Home & Garden > Lawn & Garden > Outdoor Power Equipment > Leaf Blowers"
	},
	{
		"CategoryName": "Home & Garden > Lawn & Garden > Outdoor Power Equipment > Outdoor Power Equipment Base Units"
	},
	{
		"CategoryName": "Home & Garden > Lawn & Garden > Outdoor Power Equipment > Outdoor Power Equipment Sets"
	},
	{
		"CategoryName": "Home & Garden > Lawn & Garden > Outdoor Power Equipment > Power Sweepers"
	},
	{
		"CategoryName": "Home & Garden > Lawn & Garden > Outdoor Power Equipment > Power Tillers & Cultivators"
	},
	{
		"CategoryName": "Home & Garden > Lawn & Garden > Outdoor Power Equipment > Pressure Washers"
	},
	{
		"CategoryName": "Home & Garden > Lawn & Garden > Outdoor Power Equipment > Snow Blowers"
	},
	{
		"CategoryName": "Home & Garden > Lawn & Garden > Outdoor Power Equipment > Tractors"
	},
	{
		"CategoryName": "Home & Garden > Lawn & Garden > Outdoor Power Equipment > Weed Trimmers"
	},
	{
		"CategoryName": "Home & Garden > Lawn & Garden > Outdoor Power Equipment Accessories > Chainsaw Accessories > Chainsaw Bars"
	},
	{
		"CategoryName": "Home & Garden > Lawn & Garden > Outdoor Power Equipment Accessories > Chainsaw Accessories > Chainsaw Chains"
	},
	{
		"CategoryName": "Home & Garden > Lawn & Garden > Outdoor Power Equipment Accessories > Grass Edger Accessories"
	},
	{
		"CategoryName": "Home & Garden > Lawn & Garden > Outdoor Power Equipment Accessories > Hedge Trimmer Accessories"
	},
	{
		"CategoryName": "Home & Garden > Lawn & Garden > Outdoor Power Equipment Accessories > Lawn Mower Accessories > Brush Mower Attachments"
	},
	{
		"CategoryName": "Home & Garden > Lawn & Garden > Outdoor Power Equipment Accessories > Lawn Mower Accessories > Lawn Mower Bags"
	},
	{
		"CategoryName": "Home & Garden > Lawn & Garden > Outdoor Power Equipment Accessories > Lawn Mower Accessories > Lawn Mower Belts"
	},
	{
		"CategoryName": "Home & Garden > Lawn & Garden > Outdoor Power Equipment Accessories > Lawn Mower Accessories > Lawn Mower Blades"
	},
	{
		"CategoryName": "Home & Garden > Lawn & Garden > Outdoor Power Equipment Accessories > Lawn Mower Accessories > Lawn Mower Covers"
	},
	{
		"CategoryName": "Home & Garden > Lawn & Garden > Outdoor Power Equipment Accessories > Lawn Mower Accessories > Lawn Mower Mulch Kits"
	},
	{
		"CategoryName": "Home & Garden > Lawn & Garden > Outdoor Power Equipment Accessories > Lawn Mower Accessories > Lawn Mower Mulch Plugs & Plates"
	},
	{
		"CategoryName": "Home & Garden > Lawn & Garden > Outdoor Power Equipment Accessories > Lawn Mower Accessories > Lawn Mower Pulleys & Idlers"
	},
	{
		"CategoryName": "Home & Garden > Lawn & Garden > Outdoor Power Equipment Accessories > Lawn Mower Accessories > Lawn Mower Tire Tubes"
	},
	{
		"CategoryName": "Home & Garden > Lawn & Garden > Outdoor Power Equipment Accessories > Lawn Mower Accessories > Lawn Mower Tires"
	},
	{
		"CategoryName": "Home & Garden > Lawn & Garden > Outdoor Power Equipment Accessories > Lawn Mower Accessories > Lawn Mower Wheels"
	},
	{
		"CategoryName": "Home & Garden > Lawn & Garden > Outdoor Power Equipment Accessories > Lawn Mower Accessories > Lawn Striping Kits"
	},
	{
		"CategoryName": "Home & Garden > Lawn & Garden > Outdoor Power Equipment Accessories > Lawn Mower Accessories > Lawn Sweepers"
	},
	{
		"CategoryName": "Home & Garden > Lawn & Garden > Outdoor Power Equipment Accessories > Leaf Blower Accessories > Leaf Blower Tubes"
	},
	{
		"CategoryName": "Home & Garden > Lawn & Garden > Outdoor Power Equipment Accessories > Multifunction Outdoor Power Equipment Attachments > Grass Edger Attachments"
	},
	{
		"CategoryName": "Home & Garden > Lawn & Garden > Outdoor Power Equipment Accessories > Multifunction Outdoor Power Equipment Attachments > Ground & Leaf Blower Attachments"
	},
	{
		"CategoryName": "Home & Garden > Lawn & Garden > Outdoor Power Equipment Accessories > Multifunction Outdoor Power Equipment Attachments > Hedge Trimmer Attachments"
	},
	{
		"CategoryName": "Home & Garden > Lawn & Garden > Outdoor Power Equipment Accessories > Multifunction Outdoor Power Equipment Attachments > Pole Saw Attachments"
	},
	{
		"CategoryName": "Home & Garden > Lawn & Garden > Outdoor Power Equipment Accessories > Multifunction Outdoor Power Equipment Attachments > Tiller & Cultivator Attachments"
	},
	{
		"CategoryName": "Home & Garden > Lawn & Garden > Outdoor Power Equipment Accessories > Multifunction Outdoor Power Equipment Attachments > Weed Trimmer Attachments"
	},
	{
		"CategoryName": "Home & Garden > Lawn & Garden > Outdoor Power Equipment Accessories > Outdoor Power Equipment Batteries"
	},
	{
		"CategoryName": "Home & Garden > Lawn & Garden > Outdoor Power Equipment Accessories > Pressure Washer Accessories"
	},
	{
		"CategoryName": "Home & Garden > Lawn & Garden > Outdoor Power Equipment Accessories > Snow Blower Accessories"
	},
	{
		"CategoryName": "Home & Garden > Lawn & Garden > Outdoor Power Equipment Accessories > Tractor Parts & Accessories > Tractor Tires"
	},
	{
		"CategoryName": "Home & Garden > Lawn & Garden > Outdoor Power Equipment Accessories > Tractor Parts & Accessories > Tractor Wheels"
	},
	{
		"CategoryName": "Home & Garden > Lawn & Garden > Outdoor Power Equipment Accessories > Weed Trimmer Accessories > Weed Trimmer Blades & Spools"
	},
	{
		"CategoryName": "Home & Garden > Lawn & Garden > Outdoor Power Equipment Accessories > Weed Trimmer Accessories > Weed Trimmer Spool Covers"
	},
	{
		"CategoryName": "Home & Garden > Lawn & Garden > Snow Removal > Ice Scrapers & Snow Brushes"
	},
	{
		"CategoryName": "Home & Garden > Lawn & Garden > Snow Removal > Snow Shovels"
	},
	{
		"CategoryName": "Home & Garden > Lawn & Garden > Watering & Irrigation > Garden Hose Fittings & Valves"
	},
	{
		"CategoryName": "Home & Garden > Lawn & Garden > Watering & Irrigation > Garden Hose Spray Nozzles"
	},
	{
		"CategoryName": "Home & Garden > Lawn & Garden > Watering & Irrigation > Garden Hoses"
	},
	{
		"CategoryName": "Home & Garden > Lawn & Garden > Watering & Irrigation > Sprinkler Accessories > Sprinkler Controls"
	},
	{
		"CategoryName": "Home & Garden > Lawn & Garden > Watering & Irrigation > Sprinkler Accessories > Sprinkler Valves"
	},
	{
		"CategoryName": "Home & Garden > Lawn & Garden > Watering & Irrigation > Sprinklers & Sprinkler Heads"
	},
	{
		"CategoryName": "Home & Garden > Lawn & Garden > Watering & Irrigation > Watering Can Accesssories"
	},
	{
		"CategoryName": "Home & Garden > Lawn & Garden > Watering & Irrigation > Watering Cans"
	},
	{
		"CategoryName": "Home & Garden > Lawn & Garden > Watering & Irrigation > Watering Globes & Spikes"
	},
	{
		"CategoryName": "Home & Garden > Lighting > Emergency Lighting"
	},
	{
		"CategoryName": "Home & Garden > Lighting > Floating & Submersible Lights"
	},
	{
		"CategoryName": "Home & Garden > Lighting > Flood & Spot Lights"
	},
	{
		"CategoryName": "Home & Garden > Lighting > In-Ground Lights"
	},
	{
		"CategoryName": "Home & Garden > Lighting > Lamps"
	},
	{
		"CategoryName": "Home & Garden > Lighting > Landscape Pathway Lighting"
	},
	{
		"CategoryName": "Home & Garden > Lighting > Light Bulbs > Compact Fluorescent Lamps"
	},
	{
		"CategoryName": "Home & Garden > Lighting > Light Bulbs > Fluorescent Tubes"
	},
	{
		"CategoryName": "Home & Garden > Lighting > Light Bulbs > Incandescent Light Bulbs"
	},
	{
		"CategoryName": "Home & Garden > Lighting > Light Bulbs > LED Light Bulbs"
	},
	{
		"CategoryName": "Home & Garden > Lighting > Light Ropes & Strings"
	},
	{
		"CategoryName": "Home & Garden > Lighting > Lighting Fixtures > Cabinet Light Fixtures"
	},
	{
		"CategoryName": "Home & Garden > Lighting > Lighting Fixtures > Ceiling Light Fixtures"
	},
	{
		"CategoryName": "Home & Garden > Lighting > Lighting Fixtures > Chandeliers"
	},
	{
		"CategoryName": "Home & Garden > Lighting > Lighting Fixtures > Wall Light Fixtures"
	},
	{
		"CategoryName": "Home & Garden > Lighting > Night Lights & Ambient Lighting"
	},
	{
		"CategoryName": "Home & Garden > Lighting > Picture Lights"
	},
	{
		"CategoryName": "Home & Garden > Lighting > Tiki Torches & Oil Lamps"
	},
	{
		"CategoryName": "Home & Garden > Lighting > Track Lighting > Track Lighting Accessories"
	},
	{
		"CategoryName": "Home & Garden > Lighting > Track Lighting > Track Lighting Fixtures"
	},
	{
		"CategoryName": "Home & Garden > Lighting > Track Lighting > Track Lighting Rails"
	},
	{
		"CategoryName": "Home & Garden > Lighting Accessories > Lamp Post Bases"
	},
	{
		"CategoryName": "Home & Garden > Lighting Accessories > Lamp Post Mounts"
	},
	{
		"CategoryName": "Home & Garden > Lighting Accessories > Lamp Shades"
	},
	{
		"CategoryName": "Home & Garden > Lighting Accessories > Lighting Timers"
	},
	{
		"CategoryName": "Home & Garden > Lighting Accessories > Oil Lamp Fuel"
	},
	{
		"CategoryName": "Home & Garden > Linens & Bedding > Bedding > Bed Canopies"
	},
	{
		"CategoryName": "Home & Garden > Linens & Bedding > Bedding > Bed Sheets"
	},
	{
		"CategoryName": "Home & Garden > Linens & Bedding > Bedding > Bedskirts"
	},
	{
		"CategoryName": "Home & Garden > Linens & Bedding > Bedding > Blankets"
	},
	{
		"CategoryName": "Home & Garden > Linens & Bedding > Bedding > Duvet Covers"
	},
	{
		"CategoryName": "Home & Garden > Linens & Bedding > Bedding > Mattress Protectors > Mattress Encasements"
	},
	{
		"CategoryName": "Home & Garden > Linens & Bedding > Bedding > Mattress Protectors > Mattress Pads"
	},
	{
		"CategoryName": "Home & Garden > Linens & Bedding > Bedding > Nap Mats"
	},
	{
		"CategoryName": "Home & Garden > Linens & Bedding > Bedding > Pillowcases & Shams"
	},
	{
		"CategoryName": "Home & Garden > Linens & Bedding > Bedding > Pillows"
	},
	{
		"CategoryName": "Home & Garden > Linens & Bedding > Bedding > Quilts & Comforters"
	},
	{
		"CategoryName": "Home & Garden > Linens & Bedding > Kitchen Linens Sets"
	},
	{
		"CategoryName": "Home & Garden > Linens & Bedding > Table Linens > Cloth Napkins"
	},
	{
		"CategoryName": "Home & Garden > Linens & Bedding > Table Linens > Doilies"
	},
	{
		"CategoryName": "Home & Garden > Linens & Bedding > Table Linens > Placemats"
	},
	{
		"CategoryName": "Home & Garden > Linens & Bedding > Table Linens > Table Runners"
	},
	{
		"CategoryName": "Home & Garden > Linens & Bedding > Table Linens > Table Skirts"
	},
	{
		"CategoryName": "Home & Garden > Linens & Bedding > Table Linens > Tablecloths"
	},
	{
		"CategoryName": "Home & Garden > Linens & Bedding > Towels > Bath Towels & Washcloths"
	},
	{
		"CategoryName": "Home & Garden > Linens & Bedding > Towels > Beach Towels"
	},
	{
		"CategoryName": "Home & Garden > Linens & Bedding > Towels > Kitchen Towels"
	},
	{
		"CategoryName": "Home & Garden > Parasols & Rain Umbrellas"
	},
	{
		"CategoryName": "Home & Garden > Plants > Aquatic Plants"
	},
	{
		"CategoryName": "Home & Garden > Plants > Flowers"
	},
	{
		"CategoryName": "Home & Garden > Plants > Indoor & Outdoor Plants"
	},
	{
		"CategoryName": "Home & Garden > Plants > Plant & Herb Growing Kits"
	},
	{
		"CategoryName": "Home & Garden > Plants > Seeds"
	},
	{
		"CategoryName": "Home & Garden > Plants > Trees"
	},
	{
		"CategoryName": "Home & Garden > Pool & Spa > Pool & Spa Accessories > Diving Boards"
	},
	{
		"CategoryName": "Home & Garden > Pool & Spa > Pool & Spa Accessories > Pool & Spa Chlorine Generators"
	},
	{
		"CategoryName": "Home & Garden > Pool & Spa > Pool & Spa Accessories > Pool & Spa Filters"
	},
	{
		"CategoryName": "Home & Garden > Pool & Spa > Pool & Spa Accessories > Pool & Spa Maintenance Kits"
	},
	{
		"CategoryName": "Home & Garden > Pool & Spa > Pool & Spa Accessories > Pool Brushes & Brooms"
	},
	{
		"CategoryName": "Home & Garden > Pool & Spa > Pool & Spa Accessories > Pool Cleaner Hoses"
	},
	{
		"CategoryName": "Home & Garden > Pool & Spa > Pool & Spa Accessories > Pool Cleaners & Chemicals"
	},
	{
		"CategoryName": "Home & Garden > Pool & Spa > Pool & Spa Accessories > Pool Cover Accessories"
	},
	{
		"CategoryName": "Home & Garden > Pool & Spa > Pool & Spa Accessories > Pool Covers & Ground Cloths"
	},
	{
		"CategoryName": "Home & Garden > Pool & Spa > Pool & Spa Accessories > Pool Deck Kits"
	},
	{
		"CategoryName": "Home & Garden > Pool & Spa > Pool & Spa Accessories > Pool Floats & Loungers"
	},
	{
		"CategoryName": "Home & Garden > Pool & Spa > Pool & Spa Accessories > Pool Heaters"
	},
	{
		"CategoryName": "Home & Garden > Pool & Spa > Pool & Spa Accessories > Pool Ladders, Steps & Ramps"
	},
	{
		"CategoryName": "Home & Garden > Pool & Spa > Pool & Spa Accessories > Pool Liners"
	},
	{
		"CategoryName": "Home & Garden > Pool & Spa > Pool & Spa Accessories > Pool Skimmers"
	},
	{
		"CategoryName": "Home & Garden > Pool & Spa > Pool & Spa Accessories > Pool Sweeps & Vacuums"
	},
	{
		"CategoryName": "Home & Garden > Pool & Spa > Pool & Spa Accessories > Pool Toys"
	},
	{
		"CategoryName": "Home & Garden > Pool & Spa > Pool & Spa Accessories > Pool Water Slides"
	},
	{
		"CategoryName": "Home & Garden > Pool & Spa > Saunas"
	},
	{
		"CategoryName": "Home & Garden > Pool & Spa > Spas"
	},
	{
		"CategoryName": "Home & Garden > Pool & Spa > Swimming Pools"
	},
	{
		"CategoryName": "Home & Garden > Smoking Accessories > Ashtrays"
	},
	{
		"CategoryName": "Home & Garden > Smoking Accessories > Cigar Cases"
	},
	{
		"CategoryName": "Home & Garden > Smoking Accessories > Cigar Cutters & Punches"
	},
	{
		"CategoryName": "Home & Garden > Smoking Accessories > Cigarette Cases"
	},
	{
		"CategoryName": "Home & Garden > Smoking Accessories > Cigarette Holders"
	},
	{
		"CategoryName": "Home & Garden > Smoking Accessories > Humidor Accessories"
	},
	{
		"CategoryName": "Home & Garden > Smoking Accessories > Humidors"
	},
	{
		"CategoryName": "Home & Garden > Umbrella Sleeves & Cases"
	},
	{
		"CategoryName": "Home & Garden > Wood Stoves"
	}
]